{
"meta":{"test_sets":[],"test_metrics":[],"learn_metrics":[{"best_value":"Min","name":"RMSE"}],"launch_mode":"Train","parameters":"","iteration_count":1000,"learn_sets":["learn"],"name":"experiment"},
"iterations":[
{"learn":[458212.5215],"iteration":0,"passed_time":0.001587579288,"remaining_time":1.585991709},
{"learn":[446244.944],"iteration":1,"passed_time":0.00299446725,"remaining_time":1.494239158},
{"learn":[435040.4727],"iteration":2,"passed_time":0.004442056894,"remaining_time":1.476243575},
{"learn":[424876.621],"iteration":3,"passed_time":0.005538754197,"remaining_time":1.379149795},
{"learn":[414612.9718],"iteration":4,"passed_time":0.006969642602,"remaining_time":1.386958878},
{"learn":[405646.8134],"iteration":5,"passed_time":0.008186914388,"remaining_time":1.356298817},
{"learn":[396559.1739],"iteration":6,"passed_time":0.009498312667,"remaining_time":1.347403497},
{"learn":[388069.8133],"iteration":7,"passed_time":0.01049734302,"remaining_time":1.301670535},
{"learn":[380173.3441],"iteration":8,"passed_time":0.01172468776,"remaining_time":1.291018397},
{"learn":[372856.3927],"iteration":9,"passed_time":0.0128446334,"remaining_time":1.271618707},
{"learn":[365821.008],"iteration":10,"passed_time":0.01404785804,"remaining_time":1.263030146},
{"learn":[359336.4654],"iteration":11,"passed_time":0.01498111011,"remaining_time":1.233444732},
{"learn":[352998.4886],"iteration":12,"passed_time":0.01597050553,"remaining_time":1.21252992},
{"learn":[347407.779],"iteration":13,"passed_time":0.01677041298,"remaining_time":1.181116229},
{"learn":[342037.0221],"iteration":14,"passed_time":0.01759287506,"remaining_time":1.155265463},
{"learn":[336872.863],"iteration":15,"passed_time":0.01838887918,"remaining_time":1.13091607},
{"learn":[331903.7764],"iteration":16,"passed_time":0.01914197124,"remaining_time":1.106856337},
{"learn":[327553.2641],"iteration":17,"passed_time":0.01986570232,"remaining_time":1.083784426},
{"learn":[323492.1662],"iteration":18,"passed_time":0.02057128136,"remaining_time":1.062127738},
{"learn":[319348.8197],"iteration":19,"passed_time":0.02131704679,"remaining_time":1.044535293},
{"learn":[315159.314],"iteration":20,"passed_time":0.02201827452,"remaining_time":1.026470988},
{"learn":[311329.3927],"iteration":21,"passed_time":0.02275720085,"remaining_time":1.011661019},
{"learn":[308255.9306],"iteration":22,"passed_time":0.02364088514,"remaining_time":1.004223686},
{"learn":[305253.8415],"iteration":23,"passed_time":0.02447794064,"remaining_time":0.9954362527},
{"learn":[302524.5163],"iteration":24,"passed_time":0.02543870191,"remaining_time":0.9921093744},
{"learn":[299774.257],"iteration":25,"passed_time":0.02613291069,"remaining_time":0.978979039},
{"learn":[296754.3902],"iteration":26,"passed_time":0.02680924805,"remaining_time":0.966125865},
{"learn":[294010.8568],"iteration":27,"passed_time":0.02744597201,"remaining_time":0.9527673139},
{"learn":[291564.1321],"iteration":28,"passed_time":0.02810637234,"remaining_time":0.9410788808},
{"learn":[288994.4035],"iteration":29,"passed_time":0.02888791373,"remaining_time":0.934042544},
{"learn":[286960.8932],"iteration":30,"passed_time":0.02981718199,"remaining_time":0.9320273983},
{"learn":[284685.0328],"iteration":31,"passed_time":0.03051502488,"remaining_time":0.9230795026},
{"learn":[282701.457],"iteration":32,"passed_time":0.03118292527,"remaining_time":0.913754204},
{"learn":[280817.4795],"iteration":33,"passed_time":0.03192053362,"remaining_time":0.9069186906},
{"learn":[279073.0965],"iteration":34,"passed_time":0.03276144616,"remaining_time":0.9032798728},
{"learn":[277243.6953],"iteration":35,"passed_time":0.03341586384,"remaining_time":0.8948025761},
{"learn":[275551.7976],"iteration":36,"passed_time":0.03406272591,"remaining_time":0.8865514879},
{"learn":[273995.983],"iteration":37,"passed_time":0.03469970448,"remaining_time":0.8784504135},
{"learn":[272419.3399],"iteration":38,"passed_time":0.03560699144,"remaining_time":0.8773927891},
{"learn":[270988.9334],"iteration":39,"passed_time":0.03638627652,"remaining_time":0.8732706364},
{"learn":[269410.5511],"iteration":40,"passed_time":0.03713294505,"remaining_time":0.8685486415},
{"learn":[268215.7924],"iteration":41,"passed_time":0.03798059128,"remaining_time":0.8663192012},
{"learn":[266867.8285],"iteration":42,"passed_time":0.03896192543,"remaining_time":0.8671293636},
{"learn":[265734.6657],"iteration":43,"passed_time":0.03984860319,"remaining_time":0.8658014693},
{"learn":[264881.8124],"iteration":44,"passed_time":0.04072708292,"remaining_time":0.8643192042},
{"learn":[263555.2109],"iteration":45,"passed_time":0.04161163007,"remaining_time":0.8629890237},
{"learn":[262699.7595],"iteration":46,"passed_time":0.04250122296,"remaining_time":0.8617801165},
{"learn":[261705.4197],"iteration":47,"passed_time":0.0434016733,"remaining_time":0.8607998538},
{"learn":[260657.8188],"iteration":48,"passed_time":0.04420111852,"remaining_time":0.8578625247},
{"learn":[259355.9026],"iteration":49,"passed_time":0.04491635351,"remaining_time":0.8534107166},
{"learn":[258418.1585],"iteration":50,"passed_time":0.04557686815,"remaining_time":0.8480872133},
{"learn":[257469.799],"iteration":51,"passed_time":0.04625594721,"remaining_time":0.8432814992},
{"learn":[256648.7903],"iteration":52,"passed_time":0.04703686042,"remaining_time":0.8404510721},
{"learn":[255752.0001],"iteration":53,"passed_time":0.04779888944,"remaining_time":0.8373657298},
{"learn":[254661.1143],"iteration":54,"passed_time":0.04857193331,"remaining_time":0.8345541269},
{"learn":[253878.5386],"iteration":55,"passed_time":0.04935067674,"remaining_time":0.8319114079},
{"learn":[252832.8425],"iteration":56,"passed_time":0.05018671127,"remaining_time":0.8302819076},
{"learn":[252322.1421],"iteration":57,"passed_time":0.05096785952,"remaining_time":0.8277883391},
{"learn":[251356.7784],"iteration":58,"passed_time":0.05176282771,"remaining_time":0.8255732352},
{"learn":[250789.8893],"iteration":59,"passed_time":0.05265601375,"remaining_time":0.8249442155},
{"learn":[250003.7566],"iteration":60,"passed_time":0.05355920366,"remaining_time":0.8244605284},
{"learn":[249488.155],"iteration":61,"passed_time":0.05466209195,"remaining_time":0.8269845524},
{"learn":[248952.7294],"iteration":62,"passed_time":0.0555006773,"remaining_time":0.8254624545},
{"learn":[248176.4539],"iteration":63,"passed_time":0.0562652753,"remaining_time":0.8228796512},
{"learn":[247556.3161],"iteration":64,"passed_time":0.05712916304,"remaining_time":0.8217810375},
{"learn":[246985.5362],"iteration":65,"passed_time":0.05796766043,"remaining_time":0.8203302249},
{"learn":[246514.7762],"iteration":66,"passed_time":0.05884714012,"remaining_time":0.8194683841},
{"learn":[245940.7598],"iteration":67,"passed_time":0.05987800964,"remaining_time":0.8206809556},
{"learn":[245247.3008],"iteration":68,"passed_time":0.06075234139,"remaining_time":0.8197163744},
{"learn":[244855.758],"iteration":69,"passed_time":0.0616169677,"remaining_time":0.8186254281},
{"learn":[244364.9058],"iteration":70,"passed_time":0.06249780453,"remaining_time":0.8177529636},
{"learn":[243666.3699],"iteration":71,"passed_time":0.0633362129,"remaining_time":0.8163334107},
{"learn":[243079.1145],"iteration":72,"passed_time":0.06403951568,"remaining_time":0.8132141238},
{"learn":[242613.2819],"iteration":73,"passed_time":0.0647649187,"remaining_time":0.8104366854},
{"learn":[242241.5679],"iteration":74,"passed_time":0.06543104779,"remaining_time":0.8069829228},
{"learn":[241816.3927],"iteration":75,"passed_time":0.0660665542,"remaining_time":0.8032302116},
{"learn":[241271.4599],"iteration":76,"passed_time":0.06670355379,"remaining_time":0.7995763655},
{"learn":[240780.9037],"iteration":77,"passed_time":0.06744104249,"remaining_time":0.7971877074},
{"learn":[240324.5296],"iteration":78,"passed_time":0.06815693842,"remaining_time":0.7945891176},
{"learn":[239833.7698],"iteration":79,"passed_time":0.06898806397,"remaining_time":0.7933627356},
{"learn":[239500.2082],"iteration":80,"passed_time":0.06996568352,"remaining_time":0.7938081871},
{"learn":[239062.6951],"iteration":81,"passed_time":0.07079202614,"remaining_time":0.7925253658},
{"learn":[238686.6681],"iteration":82,"passed_time":0.0715160268,"remaining_time":0.7901228503},
{"learn":[238306.8489],"iteration":83,"passed_time":0.07229024085,"remaining_time":0.7883078645},
{"learn":[238027.1324],"iteration":84,"passed_time":0.07296698169,"remaining_time":0.785468097},
{"learn":[237772.9873],"iteration":85,"passed_time":0.07360766381,"remaining_time":0.7822954038},
{"learn":[237326.5468],"iteration":86,"passed_time":0.07425480045,"remaining_time":0.779248653},
{"learn":[236982.992],"iteration":87,"passed_time":0.07489649464,"remaining_time":0.7762000353},
{"learn":[236624.0324],"iteration":88,"passed_time":0.075538155,"remaining_time":0.7732051596},
{"learn":[236285.0933],"iteration":89,"passed_time":0.07619380411,"remaining_time":0.7704040193},
{"learn":[235997.6732],"iteration":90,"passed_time":0.07682768416,"remaining_time":0.7674325813},
{"learn":[235667.507],"iteration":91,"passed_time":0.07750909254,"remaining_time":0.7649810437},
{"learn":[235380.4888],"iteration":92,"passed_time":0.07830799219,"remaining_time":0.7637134292},
{"learn":[235027.4019],"iteration":93,"passed_time":0.07895462457,"remaining_time":0.76098819},
{"learn":[234656.6602],"iteration":94,"passed_time":0.0796375507,"remaining_time":0.7586524566},
{"learn":[234312.5854],"iteration":95,"passed_time":0.08029349929,"remaining_time":0.7560971183},
{"learn":[234241.2971],"iteration":96,"passed_time":0.0807441518,"remaining_time":0.7516697843},
{"learn":[233849.4882],"iteration":97,"passed_time":0.08156041791,"remaining_time":0.7506887444},
{"learn":[233518.5818],"iteration":98,"passed_time":0.08244198797,"remaining_time":0.7503053653},
{"learn":[233143.3745],"iteration":99,"passed_time":0.08320093876,"remaining_time":0.7488084489},
{"learn":[232868.7505],"iteration":100,"passed_time":0.08384189225,"remaining_time":0.7462758528},
{"learn":[232703.9849],"iteration":101,"passed_time":0.08447652084,"remaining_time":0.7437246639},
{"learn":[232293.5694],"iteration":102,"passed_time":0.08524553782,"remaining_time":0.7423810429},
{"learn":[232143.0918],"iteration":103,"passed_time":0.0861307776,"remaining_time":0.7420497763},
{"learn":[231772.0661],"iteration":104,"passed_time":0.08704270433,"remaining_time":0.7419354322},
{"learn":[231602.0011],"iteration":105,"passed_time":0.08797091636,"remaining_time":0.7419433889},
{"learn":[231146.2109],"iteration":106,"passed_time":0.08892567111,"remaining_time":0.7421553673},
{"learn":[230941.7479],"iteration":107,"passed_time":0.08992478978,"remaining_time":0.7427121526},
{"learn":[230701.8446],"iteration":108,"passed_time":0.09098673138,"remaining_time":0.7437539235},
{"learn":[230542.31],"iteration":109,"passed_time":0.09201253593,"remaining_time":0.7444650634},
{"learn":[230165.5294],"iteration":110,"passed_time":0.09304779237,"remaining_time":0.7452206074},
{"learn":[229669.0247],"iteration":111,"passed_time":0.09401570185,"remaining_time":0.7454102075},
{"learn":[229407.7324],"iteration":112,"passed_time":0.09497553973,"remaining_time":0.7455159623},
{"learn":[229162.2531],"iteration":113,"passed_time":0.09592584416,"remaining_time":0.7455289291},
{"learn":[228946.6294],"iteration":114,"passed_time":0.09681871397,"remaining_time":0.7450831466},
{"learn":[228766.7714],"iteration":115,"passed_time":0.09757832357,"remaining_time":0.743614121},
{"learn":[228130.4084],"iteration":116,"passed_time":0.09834136963,"remaining_time":0.7421831571},
{"learn":[227790.2689],"iteration":117,"passed_time":0.09927795561,"remaining_time":0.7420606512},
{"learn":[227457.101],"iteration":118,"passed_time":0.1002336462,"remaining_time":0.7420659018},
{"learn":[227285.1059],"iteration":119,"passed_time":0.1012544399,"remaining_time":0.7425325595},
{"learn":[227064.7989],"iteration":120,"passed_time":0.1021836541,"remaining_time":0.7423093547},
{"learn":[226922.9315],"iteration":121,"passed_time":0.102899185,"remaining_time":0.7405367574},
{"learn":[226554.9755],"iteration":122,"passed_time":0.1035359274,"remaining_time":0.7382195802},
{"learn":[226363.454],"iteration":123,"passed_time":0.1041532384,"remaining_time":0.7357922324},
{"learn":[226248.2633],"iteration":124,"passed_time":0.1048249021,"remaining_time":0.7337743149},
{"learn":[226030.341],"iteration":125,"passed_time":0.1055474157,"remaining_time":0.7321304865},
{"learn":[225747.3541],"iteration":126,"passed_time":0.1062175026,"remaining_time":0.7301407854},
{"learn":[225413.6789],"iteration":127,"passed_time":0.1069030507,"remaining_time":0.7282770332},
{"learn":[225194.3936],"iteration":128,"passed_time":0.1075805793,"remaining_time":0.7263773997},
{"learn":[224882.8655],"iteration":129,"passed_time":0.108221004,"remaining_time":0.7242482572},
{"learn":[224667.3754],"iteration":130,"passed_time":0.1088871808,"remaining_time":0.7223126724},
{"learn":[224527.4716],"iteration":131,"passed_time":0.1095389575,"remaining_time":0.7203016297},
{"learn":[224267.0543],"iteration":132,"passed_time":0.1102472569,"remaining_time":0.7186794866},
{"learn":[223840.8682],"iteration":133,"passed_time":0.110887344,"remaining_time":0.7166301482},
{"learn":[223648.5536],"iteration":134,"passed_time":0.1115632202,"remaining_time":0.7148310032},
{"learn":[223481.5346],"iteration":135,"passed_time":0.1122779195,"remaining_time":0.7132950183},
{"learn":[223015.9872],"iteration":136,"passed_time":0.1131172955,"remaining_time":0.7125563941},
{"learn":[222686.6495],"iteration":137,"passed_time":0.1138245575,"remaining_time":0.7109910765},
{"learn":[222274.1372],"iteration":138,"passed_time":0.1146472713,"remaining_time":0.7101532419},
{"learn":[222073.0115],"iteration":139,"passed_time":0.1154412944,"remaining_time":0.70913938},
{"learn":[221871.8231],"iteration":140,"passed_time":0.1160900143,"remaining_time":0.7072434206},
{"learn":[221816.3264],"iteration":141,"passed_time":0.1167262038,"remaining_time":0.7052893156},
{"learn":[221605.4672],"iteration":142,"passed_time":0.1173757156,"remaining_time":0.7034334847},
{"learn":[221522.4098],"iteration":143,"passed_time":0.1180338768,"remaining_time":0.7016458229},
{"learn":[221273.1443],"iteration":144,"passed_time":0.1186726697,"remaining_time":0.6997595352},
{"learn":[220969.0926],"iteration":145,"passed_time":0.1193243279,"remaining_time":0.6979655891},
{"learn":[220660.035],"iteration":146,"passed_time":0.1199652133,"remaining_time":0.6961246734},
{"learn":[220415.3618],"iteration":147,"passed_time":0.1206129098,"remaining_time":0.6943391834},
{"learn":[220260.2601],"iteration":148,"passed_time":0.1214884349,"remaining_time":0.6938701884},
{"learn":[219890.4176],"iteration":149,"passed_time":0.122352969,"remaining_time":0.6933334907},
{"learn":[219795.9334],"iteration":150,"passed_time":0.1232624296,"remaining_time":0.6930450513},
{"learn":[219482.1175],"iteration":151,"passed_time":0.1239018839,"remaining_time":0.6912420889},
{"learn":[219245.5519],"iteration":152,"passed_time":0.124538584,"remaining_time":0.689439089},
{"learn":[219103.9557],"iteration":153,"passed_time":0.1252455974,"remaining_time":0.6880375027},
{"learn":[218919.467],"iteration":154,"passed_time":0.1259114644,"remaining_time":0.686420564},
{"learn":[218831.3137],"iteration":155,"passed_time":0.1267091796,"remaining_time":0.6855291514},
{"learn":[218404.5455],"iteration":156,"passed_time":0.1275315434,"remaining_time":0.684771281},
{"learn":[218159.8461],"iteration":157,"passed_time":0.1282917481,"remaining_time":0.6836813411},
{"learn":[217974.228],"iteration":158,"passed_time":0.1289896871,"remaining_time":0.6822662068},
{"learn":[217790.9489],"iteration":159,"passed_time":0.1296289174,"remaining_time":0.6805518163},
{"learn":[217516.9955],"iteration":160,"passed_time":0.1303764121,"remaining_time":0.6794149674},
{"learn":[217384.3887],"iteration":161,"passed_time":0.1311706684,"remaining_time":0.6785248157},
{"learn":[217080.6883],"iteration":162,"passed_time":0.1319327815,"remaining_time":0.6774707859},
{"learn":[216865.9143],"iteration":163,"passed_time":0.1328070588,"remaining_time":0.67699208},
{"learn":[216437.6758],"iteration":164,"passed_time":0.1335474149,"remaining_time":0.6758308571},
{"learn":[216286.6662],"iteration":165,"passed_time":0.1342524348,"remaining_time":0.6744971725},
{"learn":[216017.8469],"iteration":166,"passed_time":0.1348973468,"remaining_time":0.6728711971},
{"learn":[215543.1239],"iteration":167,"passed_time":0.1355468965,"remaining_time":0.6712798682},
{"learn":[215213.4949],"iteration":168,"passed_time":0.1362057787,"remaining_time":0.6697455746},
{"learn":[214838.5349],"iteration":169,"passed_time":0.136837245,"remaining_time":0.6680877258},
{"learn":[214585.156],"iteration":170,"passed_time":0.1374966027,"remaining_time":0.6665770972},
{"learn":[214422.1016],"iteration":171,"passed_time":0.1381531948,"remaining_time":0.6650630539},
{"learn":[214259.3181],"iteration":172,"passed_time":0.138799955,"remaining_time":0.6635119236},
{"learn":[214167.0878],"iteration":173,"passed_time":0.1394339739,"remaining_time":0.6619107038},
{"learn":[213938.3471],"iteration":174,"passed_time":0.1401466503,"remaining_time":0.6606913512},
{"learn":[213749.4895],"iteration":175,"passed_time":0.1408785384,"remaining_time":0.6595677026},
{"learn":[213516.6905],"iteration":176,"passed_time":0.1416600082,"remaining_time":0.6586790213},
{"learn":[213341.3608],"iteration":177,"passed_time":0.1424638963,"remaining_time":0.6578950716},
{"learn":[213238.0121],"iteration":178,"passed_time":0.1434743614,"remaining_time":0.6580583836},
{"learn":[213026.8967],"iteration":179,"passed_time":0.1443498483,"remaining_time":0.6575937535},
{"learn":[212921.6331],"iteration":180,"passed_time":0.1451825817,"remaining_time":0.6569311294},
{"learn":[212803.6444],"iteration":181,"passed_time":0.146048526,"remaining_time":0.6564159026},
{"learn":[212460.77],"iteration":182,"passed_time":0.1470684031,"remaining_time":0.6565840728},
{"learn":[212330.0396],"iteration":183,"passed_time":0.1479696276,"remaining_time":0.6562131311},
{"learn":[212172.2615],"iteration":184,"passed_time":0.1490535701,"remaining_time":0.6566414034},
{"learn":[212071.9128],"iteration":185,"passed_time":0.1500530645,"remaining_time":0.6566838413},
{"learn":[211930.9845],"iteration":186,"passed_time":0.1511080031,"remaining_time":0.6569561848},
{"learn":[211865.3637],"iteration":187,"passed_time":0.1520684781,"remaining_time":0.6568064054},
{"learn":[211388.9048],"iteration":188,"passed_time":0.1530028875,"remaining_time":0.6565361999},
{"learn":[211178.3899],"iteration":189,"passed_time":0.1538660787,"remaining_time":0.6559553882},
{"learn":[210902.9916],"iteration":190,"passed_time":0.1545518826,"remaining_time":0.6546202775},
{"learn":[210840.2578],"iteration":191,"passed_time":0.1551758058,"remaining_time":0.6530315159},
{"learn":[210670.4478],"iteration":192,"passed_time":0.1559830854,"remaining_time":0.6522194297},
{"learn":[210230.9213],"iteration":193,"passed_time":0.1568422953,"remaining_time":0.6516231443},
{"learn":[209920.6599],"iteration":194,"passed_time":0.1574858113,"remaining_time":0.650133734},
{"learn":[209812.8244],"iteration":195,"passed_time":0.1582138713,"remaining_time":0.6489997578},
{"learn":[209687.477],"iteration":196,"passed_time":0.1588952932,"remaining_time":0.6476797992},
{"learn":[209457.2423],"iteration":197,"passed_time":0.1596099752,"remaining_time":0.6465010105},
{"learn":[209336.8739],"iteration":198,"passed_time":0.1603293823,"remaining_time":0.6453459058},
{"learn":[209121.8351],"iteration":199,"passed_time":0.1611352828,"remaining_time":0.6445411311},
{"learn":[209056.3706],"iteration":200,"passed_time":0.1620014571,"remaining_time":0.6439759414},
{"learn":[208983.3861],"iteration":201,"passed_time":0.1629374195,"remaining_time":0.6436834692},
{"learn":[208952.6693],"iteration":202,"passed_time":0.163801209,"remaining_time":0.6431012983},
{"learn":[208793.0963],"iteration":203,"passed_time":0.1648510834,"remaining_time":0.6432424627},
{"learn":[208654.8063],"iteration":204,"passed_time":0.1657161477,"remaining_time":0.6426553047},
{"learn":[208493.6724],"iteration":205,"passed_time":0.1664684962,"remaining_time":0.6416310001},
{"learn":[208378.8359],"iteration":206,"passed_time":0.1671783422,"remaining_time":0.6404464994},
{"learn":[208143.1272],"iteration":207,"passed_time":0.1678408215,"remaining_time":0.639086205},
{"learn":[207940.2977],"iteration":208,"passed_time":0.1685127185,"remaining_time":0.6377682314},
{"learn":[207863.2949],"iteration":209,"passed_time":0.1691494001,"remaining_time":0.6363239337},
{"learn":[207724.9485],"iteration":210,"passed_time":0.1697977283,"remaining_time":0.6349308418},
{"learn":[207631.6768],"iteration":211,"passed_time":0.1704455789,"remaining_time":0.6335430009},
{"learn":[207478.9501],"iteration":212,"passed_time":0.1711444353,"remaining_time":0.6323505661},
{"learn":[207293.709],"iteration":213,"passed_time":0.1718326301,"remaining_time":0.6311235853},
{"learn":[207221.73],"iteration":214,"passed_time":0.1724412993,"remaining_time":0.6296112555},
{"learn":[207036.0182],"iteration":215,"passed_time":0.1730821919,"remaining_time":0.628224252},
{"learn":[206959.9876],"iteration":216,"passed_time":0.1737348771,"remaining_time":0.6268866762},
{"learn":[206717.5728],"iteration":217,"passed_time":0.1751137352,"remaining_time":0.6281602794},
{"learn":[206400.1586],"iteration":218,"passed_time":0.1759498634,"remaining_time":0.6274741703},
{"learn":[206252.8074],"iteration":219,"passed_time":0.1768777891,"remaining_time":0.6271121613},
{"learn":[206114.7882],"iteration":220,"passed_time":0.1777246106,"remaining_time":0.6264591477},
{"learn":[205982.0564],"iteration":221,"passed_time":0.1784080331,"remaining_time":0.6252317557},
{"learn":[205910.372],"iteration":222,"passed_time":0.1792542838,"remaining_time":0.6245765851},
{"learn":[205741.9078],"iteration":223,"passed_time":0.1799225673,"remaining_time":0.6233031796},
{"learn":[205634.2674],"iteration":224,"passed_time":0.180571258,"remaining_time":0.6219676665},
{"learn":[205590.9393],"iteration":225,"passed_time":0.1812344613,"remaining_time":0.6206879338},
{"learn":[205395.2696],"iteration":226,"passed_time":0.181911137,"remaining_time":0.6194595105},
{"learn":[204972.6537],"iteration":227,"passed_time":0.1825969953,"remaining_time":0.6182670192},
{"learn":[204894.3121],"iteration":228,"passed_time":0.1832141025,"remaining_time":0.6168474806},
{"learn":[204550.6973],"iteration":229,"passed_time":0.1838690099,"remaining_time":0.6155614678},
{"learn":[204325.7779],"iteration":230,"passed_time":0.1845492837,"remaining_time":0.6143653643},
{"learn":[204133.2148],"iteration":231,"passed_time":0.1852746792,"remaining_time":0.613323076},
{"learn":[203990.0339],"iteration":232,"passed_time":0.1861151801,"remaining_time":0.6126624169},
{"learn":[203911.2813],"iteration":233,"passed_time":0.1869960419,"remaining_time":0.6121323421},
{"learn":[203820.917],"iteration":234,"passed_time":0.1880613067,"remaining_time":0.6121995728},
{"learn":[203736.7341],"iteration":235,"passed_time":0.1889697966,"remaining_time":0.6117496805},
{"learn":[203660.352],"iteration":236,"passed_time":0.1899807581,"remaining_time":0.6116258161},
{"learn":[203547.62],"iteration":237,"passed_time":0.1908602869,"remaining_time":0.6110736917},
{"learn":[203470.2518],"iteration":238,"passed_time":0.19200231,"remaining_time":0.6113546356},
{"learn":[203401.334],"iteration":239,"passed_time":0.1929861964,"remaining_time":0.6111229552},
{"learn":[203337.0167],"iteration":240,"passed_time":0.1938685595,"remaining_time":0.6105652974},
{"learn":[203221.0696],"iteration":241,"passed_time":0.1948375363,"remaining_time":0.6102762499},
{"learn":[203158.0662],"iteration":242,"passed_time":0.1958545634,"remaining_time":0.6101312942},
{"learn":[203096.6854],"iteration":243,"passed_time":0.1969907138,"remaining_time":0.6103482773},
{"learn":[202906.1271],"iteration":244,"passed_time":0.1983765122,"remaining_time":0.6113235376},
{"learn":[202684.2082],"iteration":245,"passed_time":0.1994572575,"remaining_time":0.6113446024},
{"learn":[202344.2863],"iteration":246,"passed_time":0.2005039006,"remaining_time":0.611252782},
{"learn":[202160.4388],"iteration":247,"passed_time":0.2015836079,"remaining_time":0.6112535207},
{"learn":[201938.5453],"iteration":248,"passed_time":0.2025282957,"remaining_time":0.6108383538},
{"learn":[201725.5936],"iteration":249,"passed_time":0.2034689506,"remaining_time":0.6104068519},
{"learn":[201578.1269],"iteration":250,"passed_time":0.2044450564,"remaining_time":0.6100770805},
{"learn":[201390.2399],"iteration":251,"passed_time":0.2053814515,"remaining_time":0.6096243083},
{"learn":[201276.6776],"iteration":252,"passed_time":0.2064212682,"remaining_time":0.6094730726},
{"learn":[201060.3774],"iteration":253,"passed_time":0.2075457977,"remaining_time":0.6095636422},
{"learn":[201016.9218],"iteration":254,"passed_time":0.2087385499,"remaining_time":0.6098439987},
{"learn":[200959.0896],"iteration":255,"passed_time":0.2097067681,"remaining_time":0.6094602948},
{"learn":[200774.2706],"iteration":256,"passed_time":0.2105834872,"remaining_time":0.6088075137},
{"learn":[200688.4857],"iteration":257,"passed_time":0.2116540168,"remaining_time":0.6087103894},
{"learn":[200613.1262],"iteration":258,"passed_time":0.2126159539,"remaining_time":0.6082950651},
{"learn":[200503.5127],"iteration":259,"passed_time":0.2134655421,"remaining_time":0.6075557735},
{"learn":[200317.3109],"iteration":260,"passed_time":0.2141271428,"remaining_time":0.6062833661},
{"learn":[200273.3515],"iteration":261,"passed_time":0.2147840693,"remaining_time":0.6050024548},
{"learn":[200088.3292],"iteration":262,"passed_time":0.2154365992,"remaining_time":0.6037139682},
{"learn":[199948.1822],"iteration":263,"passed_time":0.2161098887,"remaining_time":0.6024881744},
{"learn":[199790.1815],"iteration":264,"passed_time":0.2168994721,"remaining_time":0.6015891018},
{"learn":[199566.2112],"iteration":265,"passed_time":0.2176387307,"remaining_time":0.6005519861},
{"learn":[199525.6441],"iteration":266,"passed_time":0.2182929425,"remaining_time":0.5992836212},
{"learn":[199356.3036],"iteration":267,"passed_time":0.2189714379,"remaining_time":0.5980861662},
{"learn":[199211.6743],"iteration":268,"passed_time":0.2196170123,"remaining_time":0.5968031077},
{"learn":[199158.9566],"iteration":269,"passed_time":0.2202646998,"remaining_time":0.5955304847},
{"learn":[198779.3177],"iteration":270,"passed_time":0.220906441,"remaining_time":0.5942464779},
{"learn":[198443.933],"iteration":271,"passed_time":0.2216317272,"remaining_time":0.5931907994},
{"learn":[198031.9537],"iteration":272,"passed_time":0.2225048913,"remaining_time":0.5925313406},
{"learn":[197962.3348],"iteration":273,"passed_time":0.2234175545,"remaining_time":0.5919749801},
{"learn":[197841.9125],"iteration":274,"passed_time":0.2241489772,"remaining_time":0.5909382126},
{"learn":[197707.9018],"iteration":275,"passed_time":0.224852515,"remaining_time":0.5898305104},
{"learn":[197393.9156],"iteration":276,"passed_time":0.2255026284,"remaining_time":0.5885862827},
{"learn":[197214.7481],"iteration":277,"passed_time":0.22618389,"remaining_time":0.5874272252},
{"learn":[197089.9322],"iteration":278,"passed_time":0.2268490818,"remaining_time":0.5862300645},
{"learn":[196632.6426],"iteration":279,"passed_time":0.2275165638,"remaining_time":0.5850425926},
{"learn":[196339.4409],"iteration":280,"passed_time":0.228308343,"remaining_time":0.5841768634},
{"learn":[196211.9077],"iteration":281,"passed_time":0.2290172666,"remaining_time":0.5831007002},
{"learn":[196136.3118],"iteration":282,"passed_time":0.2296923455,"remaining_time":0.5819413842},
{"learn":[196028.3595],"iteration":283,"passed_time":0.2303593211,"remaining_time":0.5807650489},
{"learn":[195602.8819],"iteration":284,"passed_time":0.2310333925,"remaining_time":0.57961009},
{"learn":[195493.4981],"iteration":285,"passed_time":0.2316800534,"remaining_time":0.5783900633},
{"learn":[195374.2648],"iteration":286,"passed_time":0.2323803157,"remaining_time":0.5773071954},
{"learn":[195323.9864],"iteration":287,"passed_time":0.2330376061,"remaining_time":0.5761207484},
{"learn":[195107.3531],"iteration":288,"passed_time":0.2338858624,"remaining_time":0.575407779},
{"learn":[194980.5713],"iteration":289,"passed_time":0.2346029256,"remaining_time":0.5743726799},
{"learn":[194864.0475],"iteration":290,"passed_time":0.235286231,"remaining_time":0.5732575181},
{"learn":[194751.7611],"iteration":291,"passed_time":0.235972636,"remaining_time":0.5721528297},
{"learn":[194647.8932],"iteration":292,"passed_time":0.2366474709,"remaining_time":0.5710230782},
{"learn":[194515.5333],"iteration":293,"passed_time":0.2375483657,"remaining_time":0.5704392727},
{"learn":[194449.431],"iteration":294,"passed_time":0.2384231059,"remaining_time":0.5697908124},
{"learn":[194291.5949],"iteration":295,"passed_time":0.2394705559,"remaining_time":0.5695515924},
{"learn":[193958.887],"iteration":296,"passed_time":0.2403252097,"remaining_time":0.5688505805},
{"learn":[193906.7261],"iteration":297,"passed_time":0.2411496863,"remaining_time":0.5680774489},
{"learn":[193700.3253],"iteration":298,"passed_time":0.2420874036,"remaining_time":0.5675694647},
{"learn":[193328.6967],"iteration":299,"passed_time":0.2431577146,"remaining_time":0.5673680006},
{"learn":[193008.0415],"iteration":300,"passed_time":0.2442718631,"remaining_time":0.5672625657},
{"learn":[192718.0958],"iteration":301,"passed_time":0.2453082007,"remaining_time":0.5669706095},
{"learn":[192626.1762],"iteration":302,"passed_time":0.2464153954,"remaining_time":0.5668367346},
{"learn":[192491.2166],"iteration":303,"passed_time":0.2475175636,"remaining_time":0.5666849483},
{"learn":[192396.1341],"iteration":304,"passed_time":0.2484436386,"remaining_time":0.5661256684},
{"learn":[192264.0131],"iteration":305,"passed_time":0.2493108567,"remaining_time":0.5654305051},
{"learn":[192202.4668],"iteration":306,"passed_time":0.2502343496,"remaining_time":0.5648612516},
{"learn":[191947.4198],"iteration":307,"passed_time":0.2511254417,"remaining_time":0.5642169014},
{"learn":[191859.1089],"iteration":308,"passed_time":0.2518318782,"remaining_time":0.563158019},
{"learn":[191349.0958],"iteration":309,"passed_time":0.2527223454,"remaining_time":0.5625110268},
{"learn":[191139.5925],"iteration":310,"passed_time":0.2535380641,"remaining_time":0.5616968688},
{"learn":[190890.8694],"iteration":311,"passed_time":0.2545080661,"remaining_time":0.5612229151},
{"learn":[190726.168],"iteration":312,"passed_time":0.2553727213,"remaining_time":0.5605145672},
{"learn":[190689.6019],"iteration":313,"passed_time":0.2560301367,"remaining_time":0.5593524643},
{"learn":[190455.2605],"iteration":314,"passed_time":0.2566820018,"remaining_time":0.5581814959},
{"learn":[190382.1759],"iteration":315,"passed_time":0.2573285359,"remaining_time":0.5570022738},
{"learn":[190127.6453],"iteration":316,"passed_time":0.2579690937,"remaining_time":0.5558135363},
{"learn":[189974.527],"iteration":317,"passed_time":0.2586107648,"remaining_time":0.5546306339},
{"learn":[189748.2289],"iteration":318,"passed_time":0.2592541907,"remaining_time":0.5534548711},
{"learn":[189507.9547],"iteration":319,"passed_time":0.2599149137,"remaining_time":0.5523191916},
{"learn":[189413.5851],"iteration":320,"passed_time":0.2606087026,"remaining_time":0.5512564146},
{"learn":[189344.4362],"iteration":321,"passed_time":0.2612499527,"remaining_time":0.5500853042},
{"learn":[189278.8624],"iteration":322,"passed_time":0.2619139398,"remaining_time":0.5489651308},
{"learn":[189194.0188],"iteration":323,"passed_time":0.2625625657,"remaining_time":0.5478157235},
{"learn":[189060.0863],"iteration":324,"passed_time":0.2632940978,"remaining_time":0.5468415876},
{"learn":[188998.0997],"iteration":325,"passed_time":0.2639385543,"remaining_time":0.5456889129},
{"learn":[188956.2892],"iteration":326,"passed_time":0.2645532311,"remaining_time":0.5444780566},
{"learn":[188890.3992],"iteration":327,"passed_time":0.2651816256,"remaining_time":0.5432989402},
{"learn":[188748.0866],"iteration":328,"passed_time":0.2658220503,"remaining_time":0.5421477074},
{"learn":[188649.2636],"iteration":329,"passed_time":0.2664892701,"remaining_time":0.5410539726},
{"learn":[188512.517],"iteration":330,"passed_time":0.2671515187,"remaining_time":0.5399527673},
{"learn":[188401.0057],"iteration":331,"passed_time":0.2678489168,"remaining_time":0.5389249289},
{"learn":[188314.2662],"iteration":332,"passed_time":0.2685547686,"remaining_time":0.537916008},
{"learn":[188205.3172],"iteration":333,"passed_time":0.2693758105,"remaining_time":0.5371385922},
{"learn":[188082.3346],"iteration":334,"passed_time":0.2700198547,"remaining_time":0.5360095623},
{"learn":[187695.1179],"iteration":335,"passed_time":0.270739764,"remaining_time":0.5350333431},
{"learn":[187600.2648],"iteration":336,"passed_time":0.271789476,"remaining_time":0.5347074855},
{"learn":[187495.3754],"iteration":337,"passed_time":0.2725925703,"remaining_time":0.5338943241},
{"learn":[187434.2951],"iteration":338,"passed_time":0.273266687,"remaining_time":0.5328297347},
{"learn":[187260.2909],"iteration":339,"passed_time":0.2739351788,"remaining_time":0.5317565236},
{"learn":[187108.5679],"iteration":340,"passed_time":0.2745682288,"remaining_time":0.5306171929},
{"learn":[186855.9009],"iteration":341,"passed_time":0.2752726352,"remaining_time":0.5296181109},
{"learn":[186746.7913],"iteration":342,"passed_time":0.2758978575,"remaining_time":0.5284690739},
{"learn":[186689.3546],"iteration":343,"passed_time":0.2765157887,"remaining_time":0.5273091785},
{"learn":[186458.9189],"iteration":344,"passed_time":0.2771622342,"remaining_time":0.5262065605},
{"learn":[186170.4849],"iteration":345,"passed_time":0.2778180492,"remaining_time":0.5251242895},
{"learn":[186082.8701],"iteration":346,"passed_time":0.2785089412,"remaining_time":0.5241104858},
{"learn":[185899.5665],"iteration":347,"passed_time":0.2791994898,"remaining_time":0.5230978948},
{"learn":[185803.4747],"iteration":348,"passed_time":0.2798748486,"remaining_time":0.522058815},
{"learn":[185682.7197],"iteration":349,"passed_time":0.2805202492,"remaining_time":0.5209661771},
{"learn":[185579.9939],"iteration":350,"passed_time":0.2811607682,"remaining_time":0.5198670615},
{"learn":[185515.7505],"iteration":351,"passed_time":0.2818644585,"remaining_time":0.518886844},
{"learn":[185389.0537],"iteration":352,"passed_time":0.2825396118,"remaining_time":0.517855889},
{"learn":[185245.4465],"iteration":353,"passed_time":0.2832618803,"remaining_time":0.5169129228},
{"learn":[185157.105],"iteration":354,"passed_time":0.284135305,"remaining_time":0.5162458359},
{"learn":[184929.5831],"iteration":355,"passed_time":0.2851057019,"remaining_time":0.5157530114},
{"learn":[184827.5487],"iteration":356,"passed_time":0.28602827,"remaining_time":0.5151713658},
{"learn":[184757.159],"iteration":357,"passed_time":0.2868514941,"remaining_time":0.5144096627},
{"learn":[184581.5049],"iteration":358,"passed_time":0.2877524341,"remaining_time":0.5137863796},
{"learn":[184495.0894],"iteration":359,"passed_time":0.2886716861,"remaining_time":0.5131941086},
{"learn":[184302.2455],"iteration":360,"passed_time":0.2894088069,"remaining_time":0.5122776388},
{"learn":[184170.4632],"iteration":361,"passed_time":0.2901596156,"remaining_time":0.5113862838},
{"learn":[184115.9943],"iteration":362,"passed_time":0.2909388711,"remaining_time":0.5105456223},
{"learn":[184019.8523],"iteration":363,"passed_time":0.2917655335,"remaining_time":0.50978813},
{"learn":[183849.7871],"iteration":364,"passed_time":0.2927975554,"remaining_time":0.5093875279},
{"learn":[183745.1648],"iteration":365,"passed_time":0.2935455939,"remaining_time":0.5084915479},
{"learn":[183688.7537],"iteration":366,"passed_time":0.294318058,"remaining_time":0.5076385033},
{"learn":[183495.8872],"iteration":367,"passed_time":0.2949757665,"remaining_time":0.5065888164},
{"learn":[183357.0942],"iteration":368,"passed_time":0.2956018737,"remaining_time":0.505487215},
{"learn":[183247.3629],"iteration":369,"passed_time":0.2962387227,"remaining_time":0.5044064737},
{"learn":[183112.5504],"iteration":370,"passed_time":0.2968822473,"remaining_time":0.5033394435},
{"learn":[183010.1986],"iteration":371,"passed_time":0.2975460011,"remaining_time":0.5023088406},
{"learn":[182879.7108],"iteration":372,"passed_time":0.2982336539,"remaining_time":0.501320378},
{"learn":[182808.8034],"iteration":373,"passed_time":0.2989678557,"remaining_time":0.5004114376},
{"learn":[182452.713],"iteration":374,"passed_time":0.2999022815,"remaining_time":0.4998371358},
{"learn":[182358.5822],"iteration":375,"passed_time":0.3008260226,"remaining_time":0.4992431864},
{"learn":[182267.5192],"iteration":376,"passed_time":0.3015833958,"remaining_time":0.4983725612},
{"learn":[182216.6926],"iteration":377,"passed_time":0.3022508254,"remaining_time":0.4973545328},
{"learn":[182071.7319],"iteration":378,"passed_time":0.3029808885,"remaining_time":0.4964409808},
{"learn":[181997.3993],"iteration":379,"passed_time":0.3036963019,"remaining_time":0.4955044925},
{"learn":[181876.6298],"iteration":380,"passed_time":0.3043452155,"remaining_time":0.4944611244},
{"learn":[181780.7469],"iteration":381,"passed_time":0.304975564,"remaining_time":0.4933897868},
{"learn":[181628.2511],"iteration":382,"passed_time":0.3056405713,"remaining_time":0.4923765862},
{"learn":[181550.3532],"iteration":383,"passed_time":0.30628454,"remaining_time":0.4913314496},
{"learn":[181379.5643],"iteration":384,"passed_time":0.3070106634,"remaining_time":0.4904196312},
{"learn":[181281.8541],"iteration":385,"passed_time":0.3079205026,"remaining_time":0.4898010068},
{"learn":[181256.2326],"iteration":386,"passed_time":0.3085830575,"remaining_time":0.488789184},
{"learn":[180985.6617],"iteration":387,"passed_time":0.3092254831,"remaining_time":0.4877474115},
{"learn":[180924.173],"iteration":388,"passed_time":0.3100119207,"remaining_time":0.4869338908},
{"learn":[180848.1304],"iteration":389,"passed_time":0.3107164915,"remaining_time":0.4859924611},
{"learn":[180766.8868],"iteration":390,"passed_time":0.3113661883,"remaining_time":0.484966774},
{"learn":[180482.2895],"iteration":391,"passed_time":0.3120510798,"remaining_time":0.4839975931},
{"learn":[180280.665],"iteration":392,"passed_time":0.3128079007,"remaining_time":0.483140956},
{"learn":[180178.3204],"iteration":393,"passed_time":0.313635532,"remaining_time":0.4823937371},
{"learn":[180020.0125],"iteration":394,"passed_time":0.314775234,"remaining_time":0.4821240926},
{"learn":[179974.3695],"iteration":395,"passed_time":0.3157094429,"remaining_time":0.4815366251},
{"learn":[179727.3267],"iteration":396,"passed_time":0.3169215134,"remaining_time":0.4813694523},
{"learn":[179591.7863],"iteration":397,"passed_time":0.3178678942,"remaining_time":0.4807951565},
{"learn":[179455.3014],"iteration":398,"passed_time":0.3187925006,"remaining_time":0.4801861976},
{"learn":[179198.5352],"iteration":399,"passed_time":0.3198138188,"remaining_time":0.4797207283},
{"learn":[179115.7504],"iteration":400,"passed_time":0.3207507591,"remaining_time":0.4791264457},
{"learn":[179061.6488],"iteration":401,"passed_time":0.3213929886,"remaining_time":0.4780920576},
{"learn":[178973.3616],"iteration":402,"passed_time":0.3221476991,"remaining_time":0.4772262441},
{"learn":[178712.0167],"iteration":403,"passed_time":0.3230471923,"remaining_time":0.4765745708},
{"learn":[178678.6032],"iteration":404,"passed_time":0.3238292173,"remaining_time":0.475749097},
{"learn":[178582.9608],"iteration":405,"passed_time":0.3246684938,"remaining_time":0.4750075993},
{"learn":[178416.2652],"iteration":406,"passed_time":0.3254120998,"remaining_time":0.4741262289},
{"learn":[178304.7729],"iteration":407,"passed_time":0.3260658444,"remaining_time":0.4731151468},
{"learn":[178034.3714],"iteration":408,"passed_time":0.3268340552,"remaining_time":0.4722712142},
{"learn":[177882.4518],"iteration":409,"passed_time":0.3274726234,"remaining_time":0.4712410922},
{"learn":[177724.7445],"iteration":410,"passed_time":0.3281096515,"remaining_time":0.4702106684},
{"learn":[177612.9323],"iteration":411,"passed_time":0.328755582,"remaining_time":0.4691948597},
{"learn":[177441.5046],"iteration":412,"passed_time":0.3295986137,"remaining_time":0.4684609837},
{"learn":[177239.3177],"iteration":413,"passed_time":0.3303932543,"remaining_time":0.4676580846},
{"learn":[176988.8019],"iteration":414,"passed_time":0.3312844408,"remaining_time":0.4669913201},
{"learn":[176913.8179],"iteration":415,"passed_time":0.3320785098,"remaining_time":0.4661871387},
{"learn":[176845.0846],"iteration":416,"passed_time":0.3327533294,"remaining_time":0.4652162855},
{"learn":[176698.9895],"iteration":417,"passed_time":0.3334124239,"remaining_time":0.4642249538},
{"learn":[176597.1],"iteration":418,"passed_time":0.3340945466,"remaining_time":0.4632671398},
{"learn":[176549.4152],"iteration":419,"passed_time":0.3347434777,"remaining_time":0.4622648025},
{"learn":[176326.8084],"iteration":420,"passed_time":0.3354282018,"remaining_time":0.4613133702},
{"learn":[176100.4329],"iteration":421,"passed_time":0.3361108448,"remaining_time":0.4603603515},
{"learn":[175966.3517],"iteration":422,"passed_time":0.3367852564,"remaining_time":0.4593973828},
{"learn":[175912.5425],"iteration":423,"passed_time":0.3375514031,"remaining_time":0.4585603966},
{"learn":[175748.0077],"iteration":424,"passed_time":0.3383235296,"remaining_time":0.4577318342},
{"learn":[175492.5321],"iteration":425,"passed_time":0.3389738292,"remaining_time":0.4567393849},
{"learn":[175323.1578],"iteration":426,"passed_time":0.3396680113,"remaining_time":0.455807425},
{"learn":[175241.2895],"iteration":427,"passed_time":0.3403469696,"remaining_time":0.4548562304},
{"learn":[175178.7926],"iteration":428,"passed_time":0.3410062123,"remaining_time":0.4538800634},
{"learn":[175039.3309],"iteration":429,"passed_time":0.3416774644,"remaining_time":0.45292129},
{"learn":[174891.1925],"iteration":430,"passed_time":0.3423577389,"remaining_time":0.451975762},
{"learn":[174735.9612],"iteration":431,"passed_time":0.3430085192,"remaining_time":0.4509926827},
{"learn":[174453.9627],"iteration":432,"passed_time":0.3436742367,"remaining_time":0.4500306979},
{"learn":[174262.0335],"iteration":433,"passed_time":0.3443437235,"remaining_time":0.4490749943},
{"learn":[174169.7341],"iteration":434,"passed_time":0.3451962072,"remaining_time":0.4483582921},
{"learn":[174051.8251],"iteration":435,"passed_time":0.3460929034,"remaining_time":0.4476981594},
{"learn":[173986.7327],"iteration":436,"passed_time":0.346906608,"remaining_time":0.4469300236},
{"learn":[173941.84],"iteration":437,"passed_time":0.3475539754,"remaining_time":0.4459482515},
{"learn":[173830.3008],"iteration":438,"passed_time":0.3484145905,"remaining_time":0.4452405131},
{"learn":[173749.0601],"iteration":439,"passed_time":0.349260167,"remaining_time":0.4445129398},
{"learn":[173708.2357],"iteration":440,"passed_time":0.3498910878,"remaining_time":0.4435127394},
{"learn":[173605.5662],"iteration":441,"passed_time":0.3505499116,"remaining_time":0.4425494359},
{"learn":[173412.1532],"iteration":442,"passed_time":0.3511736995,"remaining_time":0.4415434551},
{"learn":[173353.9906],"iteration":443,"passed_time":0.3519594344,"remaining_time":0.4407419945},
{"learn":[173257.2236],"iteration":444,"passed_time":0.3528242064,"remaining_time":0.4400391787},
{"learn":[173140.5931],"iteration":445,"passed_time":0.3536234518,"remaining_time":0.4392542428},
{"learn":[172969.4383],"iteration":446,"passed_time":0.3542973897,"remaining_time":0.4383142204},
{"learn":[172695.9137],"iteration":447,"passed_time":0.3550347431,"remaining_time":0.4374535227},
{"learn":[172557.0667],"iteration":448,"passed_time":0.3557100955,"remaining_time":0.4365172886},
{"learn":[172377.4056],"iteration":449,"passed_time":0.3563784296,"remaining_time":0.4355736362},
{"learn":[172202.4124],"iteration":450,"passed_time":0.35714319,"remaining_time":0.4347485838},
{"learn":[172059.5157],"iteration":451,"passed_time":0.3579832998,"remaining_time":0.4340151511},
{"learn":[171923.9494],"iteration":452,"passed_time":0.3587801259,"remaining_time":0.433228982},
{"learn":[171787.7829],"iteration":453,"passed_time":0.359472548,"remaining_time":0.4323172053},
{"learn":[171712.4153],"iteration":454,"passed_time":0.3604858271,"remaining_time":0.431790716},
{"learn":[171400.6307],"iteration":455,"passed_time":0.3615815316,"remaining_time":0.4313604236},
{"learn":[171313.2145],"iteration":456,"passed_time":0.362611295,"remaining_time":0.4308488691},
{"learn":[171230.9252],"iteration":457,"passed_time":0.3638110183,"remaining_time":0.4305361833},
{"learn":[171053.2814],"iteration":458,"passed_time":0.3648927707,"remaining_time":0.430080586},
{"learn":[170958.0488],"iteration":459,"passed_time":0.3658600193,"remaining_time":0.4294878487},
{"learn":[170804.0029],"iteration":460,"passed_time":0.3668403015,"remaining_time":0.4289087256},
{"learn":[170671.3177],"iteration":461,"passed_time":0.3677542506,"remaining_time":0.4282506208},
{"learn":[170619.8678],"iteration":462,"passed_time":0.3687190473,"remaining_time":0.4276503853},
{"learn":[170491.2557],"iteration":463,"passed_time":0.369404354,"remaining_time":0.4267257193},
{"learn":[170271.8036],"iteration":464,"passed_time":0.3701507768,"remaining_time":0.4258723991},
{"learn":[170020.2628],"iteration":465,"passed_time":0.3709260959,"remaining_time":0.4250526506},
{"learn":[169966.1406],"iteration":466,"passed_time":0.3716686531,"remaining_time":0.4241957004},
{"learn":[169808.4901],"iteration":467,"passed_time":0.3723253079,"remaining_time":0.4232415893},
{"learn":[169691.9125],"iteration":468,"passed_time":0.3729770736,"remaining_time":0.4222832113},
{"learn":[169484.954],"iteration":469,"passed_time":0.3736418637,"remaining_time":0.421340825},
{"learn":[169368.1394],"iteration":470,"passed_time":0.3743041201,"remaining_time":0.4203967718},
{"learn":[169118.5491],"iteration":471,"passed_time":0.3749725311,"remaining_time":0.4194607975},
{"learn":[168970.2246],"iteration":472,"passed_time":0.3758214722,"remaining_time":0.4187270948},
{"learn":[168849.7063],"iteration":473,"passed_time":0.3771421696,"remaining_time":0.418516416},
{"learn":[168709.3676],"iteration":474,"passed_time":0.3782095426,"remaining_time":0.4180210734},
{"learn":[168524.1602],"iteration":475,"passed_time":0.3791863784,"remaining_time":0.4174236602},
{"learn":[168337.6908],"iteration":476,"passed_time":0.380152524,"remaining_time":0.4168129351},
{"learn":[168205.0534],"iteration":477,"passed_time":0.3809857456,"remaining_time":0.4160555632},
{"learn":[168063.2312],"iteration":478,"passed_time":0.3820144286,"remaining_time":0.4155104746},
{"learn":[167943.0176],"iteration":479,"passed_time":0.3831279052,"remaining_time":0.4150552306},
{"learn":[167781.9533],"iteration":480,"passed_time":0.3842281625,"remaining_time":0.4145829861},
{"learn":[167632.6992],"iteration":481,"passed_time":0.3849495578,"remaining_time":0.4137009771},
{"learn":[167494.4529],"iteration":482,"passed_time":0.3857038343,"remaining_time":0.4128548289},
{"learn":[167364.3492],"iteration":483,"passed_time":0.38641662,"remaining_time":0.4119648263},
{"learn":[167239.7545],"iteration":484,"passed_time":0.3871816571,"remaining_time":0.4111310379},
{"learn":[167191.7993],"iteration":485,"passed_time":0.3878977282,"remaining_time":0.4102457455},
{"learn":[167143.2405],"iteration":486,"passed_time":0.3885942026,"remaining_time":0.4093405049},
{"learn":[167006.6291],"iteration":487,"passed_time":0.3893194008,"remaining_time":0.4084662566},
{"learn":[166806.2918],"iteration":488,"passed_time":0.3900625036,"remaining_time":0.4076113279},
{"learn":[166649.7678],"iteration":489,"passed_time":0.3909368485,"remaining_time":0.4068934546},
{"learn":[166497.9347],"iteration":490,"passed_time":0.3919272396,"remaining_time":0.4062952444},
{"learn":[166432.6574],"iteration":491,"passed_time":0.3927788483,"remaining_time":0.4055521442},
{"learn":[166226.2653],"iteration":492,"passed_time":0.3937387336,"remaining_time":0.4049199552},
{"learn":[166126.8907],"iteration":493,"passed_time":0.3945971343,"remaining_time":0.4041824898},
{"learn":[165977.4771],"iteration":494,"passed_time":0.3953767823,"remaining_time":0.403364192},
{"learn":[165898.1418],"iteration":495,"passed_time":0.3960833492,"remaining_time":0.4024717903},
{"learn":[165802.8642],"iteration":496,"passed_time":0.3967803745,"remaining_time":0.4015704796},
{"learn":[165697.6901],"iteration":497,"passed_time":0.397517907,"remaining_time":0.4007108219},
{"learn":[165549.9526],"iteration":498,"passed_time":0.3983323092,"remaining_time":0.3999288315},
{"learn":[165439.422],"iteration":499,"passed_time":0.3992949803,"remaining_time":0.3992949803},
{"learn":[165321.4335],"iteration":500,"passed_time":0.4000022348,"remaining_time":0.3984054195},
{"learn":[165225.8378],"iteration":501,"passed_time":0.4007027931,"remaining_time":0.3975099421},
{"learn":[165148.2745],"iteration":502,"passed_time":0.4013642963,"remaining_time":0.3965766506},
{"learn":[165071.5315],"iteration":503,"passed_time":0.4020590029,"remaining_time":0.395677114},
{"learn":[164997.4555],"iteration":504,"passed_time":0.4027069586,"remaining_time":0.3947325634},
{"learn":[164895.9367],"iteration":505,"passed_time":0.403381426,"remaining_time":0.3938150681},
{"learn":[164805.6118],"iteration":506,"passed_time":0.4040098205,"remaining_time":0.3928537308},
{"learn":[164712.5469],"iteration":507,"passed_time":0.4046440108,"remaining_time":0.3918993175},
{"learn":[164640.7637],"iteration":508,"passed_time":0.4053935784,"remaining_time":0.3910574597},
{"learn":[164554.2345],"iteration":509,"passed_time":0.4064188167,"remaining_time":0.3904808239},
{"learn":[164497.2557],"iteration":510,"passed_time":0.4072956939,"remaining_time":0.3897604586},
{"learn":[164339.4186],"iteration":511,"passed_time":0.4083036381,"remaining_time":0.3891644051},
{"learn":[164110.2366],"iteration":512,"passed_time":0.4095122942,"remaining_time":0.3887572851},
{"learn":[163998.3287],"iteration":513,"passed_time":0.4104889024,"remaining_time":0.3881276392},
{"learn":[163900.6351],"iteration":514,"passed_time":0.4114774128,"remaining_time":0.3875078548},
{"learn":[163764.4321],"iteration":515,"passed_time":0.4125098393,"remaining_time":0.3869278337},
{"learn":[163602.9232],"iteration":516,"passed_time":0.4136815859,"remaining_time":0.3864762204},
{"learn":[163383.8495],"iteration":517,"passed_time":0.4148015724,"remaining_time":0.3859736639},
{"learn":[163285.1462],"iteration":518,"passed_time":0.4157470309,"remaining_time":0.3853069786},
{"learn":[163100.2779],"iteration":519,"passed_time":0.4166990575,"remaining_time":0.3846452839},
{"learn":[162958.889],"iteration":520,"passed_time":0.4177507492,"remaining_time":0.3840741053},
{"learn":[162771.7214],"iteration":521,"passed_time":0.4188798059,"remaining_time":0.3835719295},
{"learn":[162655.7609],"iteration":522,"passed_time":0.4198175393,"remaining_time":0.3828928609},
{"learn":[162594.0025],"iteration":523,"passed_time":0.4208377685,"remaining_time":0.3822877439},
{"learn":[162436.0276],"iteration":524,"passed_time":0.4221990936,"remaining_time":0.3819896561},
{"learn":[162204.6365],"iteration":525,"passed_time":0.4232103599,"remaining_time":0.3813720734},
{"learn":[162113.6913],"iteration":526,"passed_time":0.4244902228,"remaining_time":0.3809940709},
{"learn":[162052.7512],"iteration":527,"passed_time":0.4255255387,"remaining_time":0.3803940422},
{"learn":[161883.261],"iteration":528,"passed_time":0.4263281451,"remaining_time":0.3795851727},
{"learn":[161763.1058],"iteration":529,"passed_time":0.4270498075,"remaining_time":0.3787045463},
{"learn":[161666.978],"iteration":530,"passed_time":0.4279336364,"remaining_time":0.3779677504},
{"learn":[161602.8395],"iteration":531,"passed_time":0.4289686696,"remaining_time":0.3773634161},
{"learn":[161506.2691],"iteration":532,"passed_time":0.4297171051,"remaining_time":0.3765063566},
{"learn":[161420.2943],"iteration":533,"passed_time":0.4304197291,"remaining_time":0.3756097262},
{"learn":[161355.8363],"iteration":534,"passed_time":0.4311435578,"remaining_time":0.3747322512},
{"learn":[161230.5712],"iteration":535,"passed_time":0.4318948009,"remaining_time":0.3738790814},
{"learn":[161039.6553],"iteration":536,"passed_time":0.4325732336,"remaining_time":0.3729635143},
{"learn":[160945.8816],"iteration":537,"passed_time":0.433221465,"remaining_time":0.3720228937},
{"learn":[160907.4944],"iteration":538,"passed_time":0.4338840956,"remaining_time":0.3710956736},
{"learn":[160828.0757],"iteration":539,"passed_time":0.4345575695,"remaining_time":0.3701786703},
{"learn":[160819.1903],"iteration":540,"passed_time":0.4353126326,"remaining_time":0.36933179},
{"learn":[160658.6652],"iteration":541,"passed_time":0.4361809126,"remaining_time":0.3685809188},
{"learn":[160535.9177],"iteration":542,"passed_time":0.4370343596,"remaining_time":0.3678171313},
{"learn":[160441.5577],"iteration":543,"passed_time":0.4376877331,"remaining_time":0.3668853057},
{"learn":[160335.9434],"iteration":544,"passed_time":0.4383629569,"remaining_time":0.3659727439},
{"learn":[160204.7628],"iteration":545,"passed_time":0.4390111754,"remaining_time":0.3650385964},
{"learn":[160120.6643],"iteration":546,"passed_time":0.4396447916,"remaining_time":0.3640934014},
{"learn":[160077.4734],"iteration":547,"passed_time":0.4402523558,"remaining_time":0.3631278555},
{"learn":[160010.3473],"iteration":548,"passed_time":0.440900789,"remaining_time":0.3621971873},
{"learn":[159901.0602],"iteration":549,"passed_time":0.4416887575,"remaining_time":0.3613817107},
{"learn":[159733.0145],"iteration":550,"passed_time":0.4428398261,"remaining_time":0.3608622177},
{"learn":[159656.3358],"iteration":551,"passed_time":0.4439373087,"remaining_time":0.3602969462},
{"learn":[159607.133],"iteration":552,"passed_time":0.4449535808,"remaining_time":0.359664106},
{"learn":[159490.6406],"iteration":553,"passed_time":0.4460012257,"remaining_time":0.3590551383},
{"learn":[159268.3873],"iteration":554,"passed_time":0.4469333343,"remaining_time":0.3583519527},
{"learn":[159212.3783],"iteration":555,"passed_time":0.4479011583,"remaining_time":0.3576764645},
{"learn":[159083.1367],"iteration":556,"passed_time":0.4490101724,"remaining_time":0.3571122197},
{"learn":[158944.1338],"iteration":557,"passed_time":0.450253832,"remaining_time":0.3566526769},
{"learn":[158828.0538],"iteration":558,"passed_time":0.4514445226,"remaining_time":0.3561485411},
{"learn":[158780.4291],"iteration":559,"passed_time":0.4524808773,"remaining_time":0.3555206893},
{"learn":[158647.7574],"iteration":560,"passed_time":0.4535925537,"remaining_time":0.3549503227},
{"learn":[158566.7323],"iteration":561,"passed_time":0.4546455975,"remaining_time":0.354332334},
{"learn":[158496.1386],"iteration":562,"passed_time":0.4557466977,"remaining_time":0.3537501011},
{"learn":[158387.2102],"iteration":563,"passed_time":0.456760313,"remaining_time":0.353098398},
{"learn":[158205.2371],"iteration":564,"passed_time":0.4578555025,"remaining_time":0.3525082187},
{"learn":[158028.5492],"iteration":565,"passed_time":0.4589340798,"remaining_time":0.351903517},
{"learn":[157959.0977],"iteration":566,"passed_time":0.4599979113,"remaining_time":0.3512858829},
{"learn":[157857.4728],"iteration":567,"passed_time":0.4612081132,"remaining_time":0.3507780016},
{"learn":[157773.3424],"iteration":568,"passed_time":0.4622249495,"remaining_time":0.3501211832},
{"learn":[157700.4358],"iteration":569,"passed_time":0.4630487174,"remaining_time":0.3493174535},
{"learn":[157533.6628],"iteration":570,"passed_time":0.4639125685,"remaining_time":0.3485437686},
{"learn":[157392.8883],"iteration":571,"passed_time":0.4647770719,"remaining_time":0.3477702566},
{"learn":[157324.8848],"iteration":572,"passed_time":0.4657992602,"remaining_time":0.3471139338},
{"learn":[157159.6138],"iteration":573,"passed_time":0.4666765302,"remaining_time":0.3463487837},
{"learn":[157071.2476],"iteration":574,"passed_time":0.467434642,"remaining_time":0.3454951702},
{"learn":[156975.5822],"iteration":575,"passed_time":0.4681650509,"remaining_time":0.3446214958},
{"learn":[156848.2123],"iteration":576,"passed_time":0.4689669735,"remaining_time":0.3438007449},
{"learn":[156794.7165],"iteration":577,"passed_time":0.4699962854,"remaining_time":0.3431460769},
{"learn":[156723.3532],"iteration":578,"passed_time":0.4707719866,"remaining_time":0.3423057105},
{"learn":[156620.3099],"iteration":579,"passed_time":0.4717060367,"remaining_time":0.3415802335},
{"learn":[156525.1354],"iteration":580,"passed_time":0.4725900465,"remaining_time":0.3408179509},
{"learn":[156471.4829],"iteration":581,"passed_time":0.4737560494,"remaining_time":0.3402577811},
{"learn":[156411.726],"iteration":582,"passed_time":0.4746661058,"remaining_time":0.3395124633},
{"learn":[156267.1903],"iteration":583,"passed_time":0.4754889674,"remaining_time":0.3387044699},
{"learn":[156203.7119],"iteration":584,"passed_time":0.4765090592,"remaining_time":0.3380363412},
{"learn":[156140.1699],"iteration":585,"passed_time":0.4775171252,"remaining_time":0.3373585151},
{"learn":[156035.5306],"iteration":586,"passed_time":0.4785636176,"remaining_time":0.3367065998},
{"learn":[155905.8696],"iteration":587,"passed_time":0.4794201236,"remaining_time":0.3359202226},
{"learn":[155838.1897],"iteration":588,"passed_time":0.4804069977,"remaining_time":0.3352245774},
{"learn":[155769.1168],"iteration":589,"passed_time":0.4815621538,"remaining_time":0.3346448866},
{"learn":[155712.476],"iteration":590,"passed_time":0.4823295779,"remaining_time":0.3337949194},
{"learn":[155639.3823],"iteration":591,"passed_time":0.4831396174,"remaining_time":0.3329746012},
{"learn":[155577.1464],"iteration":592,"passed_time":0.4840742131,"remaining_time":0.3322398056},
{"learn":[155496.4917],"iteration":593,"passed_time":0.4850348255,"remaining_time":0.3315221198},
{"learn":[155420.6149],"iteration":594,"passed_time":0.4860959011,"remaining_time":0.3308719999},
{"learn":[155346.4285],"iteration":595,"passed_time":0.4869525145,"remaining_time":0.3300819058},
{"learn":[155187.826],"iteration":596,"passed_time":0.4879577932,"remaining_time":0.3293919441},
{"learn":[155143.7215],"iteration":597,"passed_time":0.4891217766,"remaining_time":0.3288076157},
{"learn":[155047.2325],"iteration":598,"passed_time":0.4900182808,"remaining_time":0.3280422882},
{"learn":[154966.8617],"iteration":599,"passed_time":0.4908713222,"remaining_time":0.3272475481},
{"learn":[154772.2357],"iteration":600,"passed_time":0.4916906401,"remaining_time":0.3264302253},
{"learn":[154680.2271],"iteration":601,"passed_time":0.4924341275,"remaining_time":0.3255627621},
{"learn":[154602.0226],"iteration":602,"passed_time":0.4932181542,"remaining_time":0.3247224},
{"learn":[154446.1545],"iteration":603,"passed_time":0.4939602058,"remaining_time":0.3238547044},
{"learn":[154378.5719],"iteration":604,"passed_time":0.4947553225,"remaining_time":0.32302207},
{"learn":[154305.4925],"iteration":605,"passed_time":0.4957657063,"remaining_time":0.3223295186},
{"learn":[154181.8621],"iteration":606,"passed_time":0.4965835091,"remaining_time":0.321511234},
{"learn":[154084.7796],"iteration":607,"passed_time":0.4973038532,"remaining_time":0.3206301159},
{"learn":[153931.9442],"iteration":608,"passed_time":0.4979623334,"remaining_time":0.3197098068},
{"learn":[153866.3544],"iteration":609,"passed_time":0.4988902213,"remaining_time":0.3189626005},
{"learn":[153724.693],"iteration":610,"passed_time":0.4998033385,"remaining_time":0.3182053988},
{"learn":[153687.7292],"iteration":611,"passed_time":0.5008405753,"remaining_time":0.3175263778},
{"learn":[153641.4064],"iteration":612,"passed_time":0.5016800353,"remaining_time":0.3167213273},
{"learn":[153550.7538],"iteration":613,"passed_time":0.5025567085,"remaining_time":0.3159395594},
{"learn":[153510.8682],"iteration":614,"passed_time":0.5036563405,"remaining_time":0.3152970587},
{"learn":[153414.5456],"iteration":615,"passed_time":0.5043888839,"remaining_time":0.3144242393},
{"learn":[153255.3394],"iteration":616,"passed_time":0.505074567,"remaining_time":0.3135227863},
{"learn":[153191.4863],"iteration":617,"passed_time":0.5057553401,"remaining_time":0.3126189966},
{"learn":[153116.8078],"iteration":618,"passed_time":0.5064974686,"remaining_time":0.3117536923},
{"learn":[153049.9381],"iteration":619,"passed_time":0.507177293,"remaining_time":0.3108505989},
{"learn":[152958.9767],"iteration":620,"passed_time":0.5078546,"remaining_time":0.3099466882},
{"learn":[152848.666],"iteration":621,"passed_time":0.5085435458,"remaining_time":0.3090505793},
{"learn":[152742.3992],"iteration":622,"passed_time":0.5092612953,"remaining_time":0.3081725655},
{"learn":[152642.9078],"iteration":623,"passed_time":0.5100336366,"remaining_time":0.3073279605},
{"learn":[152591.9844],"iteration":624,"passed_time":0.511139993,"remaining_time":0.3066839958},
{"learn":[152498.8246],"iteration":625,"passed_time":0.5118741119,"remaining_time":0.3058161627},
{"learn":[152445.6881],"iteration":626,"passed_time":0.5125015606,"remaining_time":0.3048852984},
{"learn":[152388.0935],"iteration":627,"passed_time":0.51318569,"remaining_time":0.3039889756},
{"learn":[152336.1169],"iteration":628,"passed_time":0.5141114961,"remaining_time":0.3032358745},
{"learn":[152187.6477],"iteration":629,"passed_time":0.5150116926,"remaining_time":0.3024671845},
{"learn":[152126.3212],"iteration":630,"passed_time":0.5160309297,"remaining_time":0.3017676911},
{"learn":[151955.3248],"iteration":631,"passed_time":0.5169689373,"remaining_time":0.3010198875},
{"learn":[151824.3749],"iteration":632,"passed_time":0.5181139919,"remaining_time":0.3003915246},
{"learn":[151737.45],"iteration":633,"passed_time":0.5192582368,"remaining_time":0.2997610641},
{"learn":[151667.6332],"iteration":634,"passed_time":0.5199951764,"remaining_time":0.2988948652},
{"learn":[151623.3728],"iteration":635,"passed_time":0.5207405576,"remaining_time":0.298033904},
{"learn":[151503.9768],"iteration":636,"passed_time":0.5214662786,"remaining_time":0.2971621022},
{"learn":[151436.4542],"iteration":637,"passed_time":0.522166511,"remaining_time":0.2962762962},
{"learn":[151358.3318],"iteration":638,"passed_time":0.5229516808,"remaining_time":0.295439056},
{"learn":[151253.9097],"iteration":639,"passed_time":0.5236023796,"remaining_time":0.2945263385},
{"learn":[151211.175],"iteration":640,"passed_time":0.5242877159,"remaining_time":0.2936338378},
{"learn":[151115.2196],"iteration":641,"passed_time":0.5250844404,"remaining_time":0.2928040961},
{"learn":[151075.8902],"iteration":642,"passed_time":0.5261926041,"remaining_time":0.2921473712},
{"learn":[151002.0577],"iteration":643,"passed_time":0.5268985984,"remaining_time":0.2912669271},
{"learn":[150912.3527],"iteration":644,"passed_time":0.527633547,"remaining_time":0.29040296},
{"learn":[150856.8506],"iteration":645,"passed_time":0.5284044535,"remaining_time":0.2895590968},
{"learn":[150769.0348],"iteration":646,"passed_time":0.5293019274,"remaining_time":0.2887845137},
{"learn":[150730.2274],"iteration":647,"passed_time":0.5301681659,"remaining_time":0.2879925839},
{"learn":[150515.4838],"iteration":648,"passed_time":0.5312861874,"remaining_time":0.2873365975},
{"learn":[150461.0379],"iteration":649,"passed_time":0.5321204361,"remaining_time":0.2865263887},
{"learn":[150419.7842],"iteration":650,"passed_time":0.5332617516,"remaining_time":0.285880724},
{"learn":[150361.0384],"iteration":651,"passed_time":0.5343295313,"remaining_time":0.2851942897},
{"learn":[150279.9688],"iteration":652,"passed_time":0.53527525,"remaining_time":0.2844418251},
{"learn":[150147.2349],"iteration":653,"passed_time":0.5360266274,"remaining_time":0.2835859527},
{"learn":[150078.1169],"iteration":654,"passed_time":0.5368011784,"remaining_time":0.2827426054},
{"learn":[149970.2078],"iteration":655,"passed_time":0.5375608268,"remaining_time":0.2818916531},
{"learn":[149910.1569],"iteration":656,"passed_time":0.5384254869,"remaining_time":0.2810958022},
{"learn":[149823.2371],"iteration":657,"passed_time":0.5393049257,"remaining_time":0.2803074234},
{"learn":[149694.6165],"iteration":658,"passed_time":0.5402433025,"remaining_time":0.2795492658},
{"learn":[149602.6807],"iteration":659,"passed_time":0.5412677072,"remaining_time":0.2788348795},
{"learn":[149522.3081],"iteration":660,"passed_time":0.5420236143,"remaining_time":0.2779818536},
{"learn":[149445.0239],"iteration":661,"passed_time":0.5427752595,"remaining_time":0.2771269452},
{"learn":[149356.8684],"iteration":662,"passed_time":0.5435205894,"remaining_time":0.2762691382},
{"learn":[149282.4359],"iteration":663,"passed_time":0.5442487982,"remaining_time":0.2754030063},
{"learn":[149254.2329],"iteration":664,"passed_time":0.5450226854,"remaining_time":0.2745603001},
{"learn":[149188.9955],"iteration":665,"passed_time":0.5459697702,"remaining_time":0.2738046595},
{"learn":[149046.9852],"iteration":666,"passed_time":0.5470748724,"remaining_time":0.2731273351},
{"learn":[149012.6641],"iteration":667,"passed_time":0.5480462105,"remaining_time":0.2723822483},
{"learn":[148899.3935],"iteration":668,"passed_time":0.5487713561,"remaining_time":0.2715146769},
{"learn":[148758.0098],"iteration":669,"passed_time":0.5495590838,"remaining_time":0.2706783547},
{"learn":[148670.0274],"iteration":670,"passed_time":0.5502907487,"remaining_time":0.269814689},
{"learn":[148633.8276],"iteration":671,"passed_time":0.5509707772,"remaining_time":0.2689262127},
{"learn":[148572.7896],"iteration":672,"passed_time":0.5516499381,"remaining_time":0.2680379343},
{"learn":[148466.0777],"iteration":673,"passed_time":0.5523160038,"remaining_time":0.2671439425},
{"learn":[148319.5103],"iteration":674,"passed_time":0.5529985827,"remaining_time":0.2662585769},
{"learn":[148133.6632],"iteration":675,"passed_time":0.5536368807,"remaining_time":0.2653525878},
{"learn":[148087.7818],"iteration":676,"passed_time":0.5544467699,"remaining_time":0.2645292566},
{"learn":[148006.719],"iteration":677,"passed_time":0.5552744092,"remaining_time":0.2637143949},
{"learn":[147881.1178],"iteration":678,"passed_time":0.5560549844,"remaining_time":0.2628772459},
{"learn":[147764.5983],"iteration":679,"passed_time":0.5567697333,"remaining_time":0.2620092863},
{"learn":[147710.3369],"iteration":680,"passed_time":0.5574053882,"remaining_time":0.2611047266},
{"learn":[147646.913],"iteration":681,"passed_time":0.558062538,"remaining_time":0.2602109781},
{"learn":[147631.1444],"iteration":682,"passed_time":0.5587303305,"remaining_time":0.259322862},
{"learn":[147601.87],"iteration":683,"passed_time":0.5594571255,"remaining_time":0.2584626486},
{"learn":[147489.5908],"iteration":684,"passed_time":0.5602507576,"remaining_time":0.2576335601},
{"learn":[147438.9804],"iteration":685,"passed_time":0.5611019347,"remaining_time":0.2568309147},
{"learn":[147381.0896],"iteration":686,"passed_time":0.5619529846,"remaining_time":0.2560280701},
{"learn":[147316.1918],"iteration":687,"passed_time":0.5626582563,"remaining_time":0.2551589767},
{"learn":[147243.0773],"iteration":688,"passed_time":0.5633185641,"remaining_time":0.254270063},
{"learn":[147145.733],"iteration":689,"passed_time":0.5641042381,"remaining_time":0.253438136},
{"learn":[147057.2011],"iteration":690,"passed_time":0.5647605496,"remaining_time":0.2525484947},
{"learn":[147021.6356],"iteration":691,"passed_time":0.5654877919,"remaining_time":0.2516910981},
{"learn":[146961.8297],"iteration":692,"passed_time":0.5662141985,"remaining_time":0.250833707},
{"learn":[146840.2173],"iteration":693,"passed_time":0.5669674248,"remaining_time":0.2499885187},
{"learn":[146743.342],"iteration":694,"passed_time":0.5677245929,"remaining_time":0.2491453249},
{"learn":[146666.2748],"iteration":695,"passed_time":0.5684008074,"remaining_time":0.2482670193},
{"learn":[146641.5536],"iteration":696,"passed_time":0.5691428372,"remaining_time":0.2474179048},
{"learn":[146628.5038],"iteration":697,"passed_time":0.5697935627,"remaining_time":0.246529593},
{"learn":[146530.2706],"iteration":698,"passed_time":0.5704943617,"remaining_time":0.2456635234},
{"learn":[146397.9939],"iteration":699,"passed_time":0.5711810334,"remaining_time":0.2447918715},
{"learn":[146356.4735],"iteration":700,"passed_time":0.5718464481,"remaining_time":0.2439116804},
{"learn":[146233.1256],"iteration":701,"passed_time":0.5726125763,"remaining_time":0.2430748543},
{"learn":[146169.9843],"iteration":702,"passed_time":0.5732689216,"remaining_time":0.2421918488},
{"learn":[146052.8977],"iteration":703,"passed_time":0.5739677802,"remaining_time":0.2413273621},
{"learn":[145963.1488],"iteration":704,"passed_time":0.5746536755,"remaining_time":0.240457921},
{"learn":[145903.7514],"iteration":705,"passed_time":0.5752986096,"remaining_time":0.2395719422},
{"learn":[145822.2639],"iteration":706,"passed_time":0.5761506962,"remaining_time":0.238772495},
{"learn":[145808.7125],"iteration":707,"passed_time":0.5770334193,"remaining_time":0.2379855345},
{"learn":[145781.8385],"iteration":708,"passed_time":0.5778214238,"remaining_time":0.2371594278},
{"learn":[145711.5469],"iteration":709,"passed_time":0.5786641546,"remaining_time":0.2363557815},
{"learn":[145617.1477],"iteration":710,"passed_time":0.5796182128,"remaining_time":0.2355972764},
{"learn":[145566.6032],"iteration":711,"passed_time":0.5805745291,"remaining_time":0.2348391354},
{"learn":[145425.1311],"iteration":712,"passed_time":0.5813985335,"remaining_time":0.2340271797},
{"learn":[145375.5869],"iteration":713,"passed_time":0.5820800826,"remaining_time":0.2331581283},
{"learn":[145332.9386],"iteration":714,"passed_time":0.582758584,"remaining_time":0.2322883866},
{"learn":[145263.4431],"iteration":715,"passed_time":0.5834151957,"remaining_time":0.2314104966},
{"learn":[145178.2816],"iteration":716,"passed_time":0.5840816727,"remaining_time":0.2305371177},
{"learn":[145064.1713],"iteration":717,"passed_time":0.5847630113,"remaining_time":0.2296701521},
{"learn":[145012.1944],"iteration":718,"passed_time":0.5854046983,"remaining_time":0.2287882062},
{"learn":[144907.2154],"iteration":719,"passed_time":0.5861679203,"remaining_time":0.2279541912},
{"learn":[144833.9019],"iteration":720,"passed_time":0.5868554093,"remaining_time":0.2270910668},
{"learn":[144686.2642],"iteration":721,"passed_time":0.5874938501,"remaining_time":0.2262095434},
{"learn":[144651.0491],"iteration":722,"passed_time":0.5881537757,"remaining_time":0.2253369237},
{"learn":[144577.9541],"iteration":723,"passed_time":0.5888413174,"remaining_time":0.2244754193},
{"learn":[144515.6337],"iteration":724,"passed_time":0.589554108,"remaining_time":0.223623972},
{"learn":[144398.6637],"iteration":725,"passed_time":0.590198394,"remaining_time":0.2227470523},
{"learn":[144361.6261],"iteration":726,"passed_time":0.590878838,"remaining_time":0.2218843505},
{"learn":[144274.2179],"iteration":727,"passed_time":0.59185599,"remaining_time":0.2211330073},
{"learn":[144142.3779],"iteration":728,"passed_time":0.5927587016,"remaining_time":0.2203533719},
{"learn":[144085.3672],"iteration":729,"passed_time":0.5934760776,"remaining_time":0.2195048506},
{"learn":[143981.7552],"iteration":730,"passed_time":0.5941809633,"remaining_time":0.2186520918},
{"learn":[143878.5696],"iteration":731,"passed_time":0.5948852973,"remaining_time":0.2177995351},
{"learn":[143768.4069],"iteration":732,"passed_time":0.5955683873,"remaining_time":0.2169396445},
{"learn":[143626.2625],"iteration":733,"passed_time":0.5962104148,"remaining_time":0.2160653547},
{"learn":[143599.8889],"iteration":734,"passed_time":0.5968494727,"remaining_time":0.2151906262},
{"learn":[143529.1984],"iteration":735,"passed_time":0.5974837758,"remaining_time":0.2143148326},
{"learn":[143452.5234],"iteration":736,"passed_time":0.5981466347,"remaining_time":0.2134498846},
{"learn":[143400.6326],"iteration":737,"passed_time":0.598798508,"remaining_time":0.2125815841},
{"learn":[143287.7453],"iteration":738,"passed_time":0.5994450606,"remaining_time":0.2117119903},
{"learn":[143217.9178],"iteration":739,"passed_time":0.6001668149,"remaining_time":0.2108694215},
{"learn":[143164.5246],"iteration":740,"passed_time":0.6008558419,"remaining_time":0.2100157396},
{"learn":[143057.0731],"iteration":741,"passed_time":0.6016334625,"remaining_time":0.2091933064},
{"learn":[142942.7373],"iteration":742,"passed_time":0.6023415397,"remaining_time":0.208346939},
{"learn":[142853.3145],"iteration":743,"passed_time":0.6030703236,"remaining_time":0.2075080683},
{"learn":[142718.9857],"iteration":744,"passed_time":0.6037401919,"remaining_time":0.2066493274},
{"learn":[142621.6871],"iteration":745,"passed_time":0.6044046797,"remaining_time":0.2057892609},
{"learn":[142522.4353],"iteration":746,"passed_time":0.6050819401,"remaining_time":0.204934044},
{"learn":[142449.8278],"iteration":747,"passed_time":0.6057690979,"remaining_time":0.2040826372},
{"learn":[142339.3363],"iteration":748,"passed_time":0.606556353,"remaining_time":0.2032652131},
{"learn":[142309.0392],"iteration":749,"passed_time":0.6074840872,"remaining_time":0.2024946957},
{"learn":[142220.2209],"iteration":750,"passed_time":0.6082268282,"remaining_time":0.2016624237},
{"learn":[142166.1695],"iteration":751,"passed_time":0.6088984111,"remaining_time":0.2008069228},
{"learn":[142105.0945],"iteration":752,"passed_time":0.6095518591,"remaining_time":0.1999459617},
{"learn":[142046.3675],"iteration":753,"passed_time":0.6102233042,"remaining_time":0.1990914228},
{"learn":[141971.1969],"iteration":754,"passed_time":0.6108889315,"remaining_time":0.1982354811},
{"learn":[141870.3342],"iteration":755,"passed_time":0.6115491524,"remaining_time":0.1973782979},
{"learn":[141790.6465],"iteration":756,"passed_time":0.6122169751,"remaining_time":0.1965240752},
{"learn":[141704.4195],"iteration":757,"passed_time":0.6129028652,"remaining_time":0.1956761126},
{"learn":[141604.0374],"iteration":758,"passed_time":0.6137444778,"remaining_time":0.1948780226},
{"learn":[141524.8602],"iteration":759,"passed_time":0.6144666552,"remaining_time":0.1940421016},
{"learn":[141420.2158],"iteration":760,"passed_time":0.6151744934,"remaining_time":0.1932019762},
{"learn":[141368.4648],"iteration":761,"passed_time":0.6158195414,"remaining_time":0.1923425864},
{"learn":[141247.9016],"iteration":762,"passed_time":0.6164919053,"remaining_time":0.1914922432},
{"learn":[141136.7268],"iteration":763,"passed_time":0.6172385115,"remaining_time":0.1906652994},
{"learn":[141085.6334],"iteration":764,"passed_time":0.6179735181,"remaining_time":0.1898350023},
{"learn":[140919.3478],"iteration":765,"passed_time":0.6186280669,"remaining_time":0.1889803755},
{"learn":[140873.8727],"iteration":766,"passed_time":0.6192711203,"remaining_time":0.1881227784},
{"learn":[140829.0384],"iteration":767,"passed_time":0.6199088197,"remaining_time":0.1872641226},
{"learn":[140740.712],"iteration":768,"passed_time":0.6205678696,"remaining_time":0.186412455},
{"learn":[140681.2924],"iteration":769,"passed_time":0.6212963598,"remaining_time":0.1855820295},
{"learn":[140629.4733],"iteration":770,"passed_time":0.6221113944,"remaining_time":0.1847775737},
{"learn":[140515.3836],"iteration":771,"passed_time":0.6229102784,"remaining_time":0.1839683206},
{"learn":[140423.1092],"iteration":772,"passed_time":0.6235967674,"remaining_time":0.1831260882},
{"learn":[140302.0271],"iteration":773,"passed_time":0.6242838262,"remaining_time":0.1822844247},
{"learn":[140182.3703],"iteration":774,"passed_time":0.6249551496,"remaining_time":0.1814385918},
{"learn":[140114.3606],"iteration":775,"passed_time":0.6256090309,"remaining_time":0.1805881739},
{"learn":[140026.0078],"iteration":776,"passed_time":0.6262611179,"remaining_time":0.1797377468},
{"learn":[139933.0936],"iteration":777,"passed_time":0.6269119509,"remaining_time":0.1788874719},
{"learn":[139865.1552],"iteration":778,"passed_time":0.6275532637,"remaining_time":0.1780350081},
{"learn":[139803.6895],"iteration":779,"passed_time":0.6282092412,"remaining_time":0.1771872219},
{"learn":[139709.3818],"iteration":780,"passed_time":0.6289068985,"remaining_time":0.1763516143},
{"learn":[139648.129],"iteration":781,"passed_time":0.6295752633,"remaining_time":0.1755081936},
{"learn":[139512.1083],"iteration":782,"passed_time":0.6302330181,"remaining_time":0.1746622796},
{"learn":[139423.8254],"iteration":783,"passed_time":0.6309025655,"remaining_time":0.1738200946},
{"learn":[139390.1304],"iteration":784,"passed_time":0.6315570914,"remaining_time":0.1729742352},
{"learn":[139202.733],"iteration":785,"passed_time":0.6322612107,"remaining_time":0.1721423653},
{"learn":[139145.6255],"iteration":786,"passed_time":0.6329366557,"remaining_time":0.1713030593},
{"learn":[139069.7322],"iteration":787,"passed_time":0.6336017449,"remaining_time":0.1704613832},
{"learn":[139009.0063],"iteration":788,"passed_time":0.6342961905,"remaining_time":0.1696280053},
{"learn":[138993.6718],"iteration":789,"passed_time":0.6349198078,"remaining_time":0.1687761514},
{"learn":[138924.9989],"iteration":790,"passed_time":0.6356482399,"remaining_time":0.1679525691},
{"learn":[138861.4714],"iteration":791,"passed_time":0.6363288951,"remaining_time":0.1671166795},
{"learn":[138822.5686],"iteration":792,"passed_time":0.6370095169,"remaining_time":0.1662811727},
{"learn":[138777.2067],"iteration":793,"passed_time":0.6379160029,"remaining_time":0.1655046557},
{"learn":[138728.622],"iteration":794,"passed_time":0.6388748255,"remaining_time":0.1647413072},
{"learn":[138653.4406],"iteration":795,"passed_time":0.6395990552,"remaining_time":0.1639173458},
{"learn":[138559.8621],"iteration":796,"passed_time":0.6402900728,"remaining_time":0.1630851754},
{"learn":[138459.7224],"iteration":797,"passed_time":0.6409404045,"remaining_time":0.1622430598},
{"learn":[138416.4458],"iteration":798,"passed_time":0.6416047171,"remaining_time":0.1614049413},
{"learn":[138321.4055],"iteration":799,"passed_time":0.64227926,"remaining_time":0.160569815},
{"learn":[138257.1355],"iteration":800,"passed_time":0.6429286736,"remaining_time":0.1597288465},
{"learn":[138207.2886],"iteration":801,"passed_time":0.6436011503,"remaining_time":0.1588940496},
{"learn":[138063.6082],"iteration":802,"passed_time":0.6442665839,"remaining_time":0.1580579291},
{"learn":[137993.0962],"iteration":803,"passed_time":0.6449274291,"remaining_time":0.1572211145},
{"learn":[137977.3422],"iteration":804,"passed_time":0.6455845557,"remaining_time":0.1563838365},
{"learn":[137882.7729],"iteration":805,"passed_time":0.646343666,"remaining_time":0.1555715524},
{"learn":[137820.2505],"iteration":806,"passed_time":0.647004644,"remaining_time":0.154735931},
{"learn":[137732.7439],"iteration":807,"passed_time":0.6476958415,"remaining_time":0.1539079227},
{"learn":[137679.8139],"iteration":808,"passed_time":0.6483528324,"remaining_time":0.1530721767},
{"learn":[137641.5103],"iteration":809,"passed_time":0.6490110302,"remaining_time":0.1522371552},
{"learn":[137573.3964],"iteration":810,"passed_time":0.6496591379,"remaining_time":0.1514002183},
{"learn":[137530.7724],"iteration":811,"passed_time":0.6502737488,"remaining_time":0.1505559911},
{"learn":[137493.0213],"iteration":812,"passed_time":0.650952762,"remaining_time":0.1497271421},
{"learn":[137389.3288],"iteration":813,"passed_time":0.6516438171,"remaining_time":0.1489014127},
{"learn":[137320.8106],"iteration":814,"passed_time":0.6523797232,"remaining_time":0.1480861948},
{"learn":[137240.6584],"iteration":815,"passed_time":0.6532316795,"remaining_time":0.1472973395},
{"learn":[137136.3348],"iteration":816,"passed_time":0.654169588,"remaining_time":0.1465275821},
{"learn":[137062.3833],"iteration":817,"passed_time":0.655062819,"remaining_time":0.1457474732},
{"learn":[137037.6061],"iteration":818,"passed_time":0.6559307361,"remaining_time":0.1449614936},
{"learn":[136987.0163],"iteration":819,"passed_time":0.6567617712,"remaining_time":0.1441672181},
{"learn":[136939.2599],"iteration":820,"passed_time":0.6576997506,"remaining_time":0.1433961697},
{"learn":[136843.0764],"iteration":821,"passed_time":0.6585877488,"remaining_time":0.1426138921},
{"learn":[136808.1037],"iteration":822,"passed_time":0.659339405,"remaining_time":0.1418020349},
{"learn":[136774.2066],"iteration":823,"passed_time":0.6600892707,"remaining_time":0.1409899413},
{"learn":[136646.6129],"iteration":824,"passed_time":0.6608211429,"remaining_time":0.1401741818},
{"learn":[136602.7366],"iteration":825,"passed_time":0.6615096119,"remaining_time":0.1393494824},
{"learn":[136527.3402],"iteration":826,"passed_time":0.6621725944,"remaining_time":0.1385197809},
{"learn":[136486.1487],"iteration":827,"passed_time":0.6628243832,"remaining_time":0.1376881569},
{"learn":[136401.816],"iteration":828,"passed_time":0.6635625549,"remaining_time":0.1368747852},
{"learn":[136376.0813],"iteration":829,"passed_time":0.6642823759,"remaining_time":0.136057836},
{"learn":[136268.9321],"iteration":830,"passed_time":0.6649300314,"remaining_time":0.1352264444},
{"learn":[136253.9697],"iteration":831,"passed_time":0.6655832643,"remaining_time":0.1343966207},
{"learn":[136209.763],"iteration":832,"passed_time":0.6662410269,"remaining_time":0.133568129},
{"learn":[136121.2385],"iteration":833,"passed_time":0.666887311,"remaining_time":0.1327377621},
{"learn":[136033.3038],"iteration":834,"passed_time":0.6676962067,"remaining_time":0.131939969},
{"learn":[135992.5683],"iteration":835,"passed_time":0.6686728053,"remaining_time":0.1311750479},
{"learn":[135936.213],"iteration":836,"passed_time":0.6695956383,"remaining_time":0.1303991506},
{"learn":[135877.8929],"iteration":837,"passed_time":0.6705472739,"remaining_time":0.1296284706},
{"learn":[135863.788],"iteration":838,"passed_time":0.6713516512,"remaining_time":0.1288291011},
{"learn":[135729.2402],"iteration":839,"passed_time":0.6722688608,"remaining_time":0.1280512116},
{"learn":[135684.6861],"iteration":840,"passed_time":0.6732016767,"remaining_time":0.1272759412},
{"learn":[135637.6509],"iteration":841,"passed_time":0.6739471447,"remaining_time":0.1264651412},
{"learn":[135554.2372],"iteration":842,"passed_time":0.6746649452,"remaining_time":0.1256493433},
{"learn":[135468.5742],"iteration":843,"passed_time":0.6754050306,"remaining_time":0.1248378967},
{"learn":[135422.7011],"iteration":844,"passed_time":0.6760897348,"remaining_time":0.1240164602},
{"learn":[135351.1628],"iteration":845,"passed_time":0.676768837,"remaining_time":0.1231943273},
{"learn":[135265.6493],"iteration":846,"passed_time":0.6774407098,"remaining_time":0.1223712262},
{"learn":[135204.1698],"iteration":847,"passed_time":0.67811655,"remaining_time":0.1215491929},
{"learn":[135125.7474],"iteration":848,"passed_time":0.6789429831,"remaining_time":0.1207542879},
{"learn":[135061.045],"iteration":849,"passed_time":0.6796207047,"remaining_time":0.1199330655},
{"learn":[135004.8213],"iteration":850,"passed_time":0.6802921502,"remaining_time":0.1191110815},
{"learn":[134995.7119],"iteration":851,"passed_time":0.6809345313,"remaining_time":0.1182844021},
{"learn":[134948.4377],"iteration":852,"passed_time":0.681583082,"remaining_time":0.1174592181},
{"learn":[134906.0013],"iteration":853,"passed_time":0.6822660879,"remaining_time":0.1166403382},
{"learn":[134859.7242],"iteration":854,"passed_time":0.6830206094,"remaining_time":0.1158339045},
{"learn":[134783.1838],"iteration":855,"passed_time":0.6837696361,"remaining_time":0.1150266678},
{"learn":[134728.697],"iteration":856,"passed_time":0.6846772457,"remaining_time":0.1142460282},
{"learn":[134710.2592],"iteration":857,"passed_time":0.6855268822,"remaining_time":0.113455498},
{"learn":[134649.9358],"iteration":858,"passed_time":0.6861922094,"remaining_time":0.1126345769},
{"learn":[134586.5322],"iteration":859,"passed_time":0.6869031578,"remaining_time":0.1118214443},
{"learn":[134518.3533],"iteration":860,"passed_time":0.6876115039,"remaining_time":0.111008129},
{"learn":[134504.8101],"iteration":861,"passed_time":0.6882665512,"remaining_time":0.1101865244},
{"learn":[134483],"iteration":862,"passed_time":0.6889552562,"remaining_time":0.109370649},
{"learn":[134448.5401],"iteration":863,"passed_time":0.6896188028,"remaining_time":0.1085511079},
{"learn":[134350.9218],"iteration":864,"passed_time":0.6902864176,"remaining_time":0.1077325623},
{"learn":[134338.4465],"iteration":865,"passed_time":0.6909124903,"remaining_time":0.1069079373},
{"learn":[134295.3303],"iteration":866,"passed_time":0.6915386292,"remaining_time":0.1060837805},
{"learn":[134270.1266],"iteration":867,"passed_time":0.6922016993,"remaining_time":0.1052656962},
{"learn":[134173.7348],"iteration":868,"passed_time":0.6928639183,"remaining_time":0.1044478404},
{"learn":[134118.1571],"iteration":869,"passed_time":0.693530162,"remaining_time":0.1036309438},
{"learn":[134066.5316],"iteration":870,"passed_time":0.6943253574,"remaining_time":0.1028334915},
{"learn":[134027.3187],"iteration":871,"passed_time":0.6950292353,"remaining_time":0.10202264},
{"learn":[133977.8182],"iteration":872,"passed_time":0.6956595831,"remaining_time":0.1012013368},
{"learn":[133929.3338],"iteration":873,"passed_time":0.6964050929,"remaining_time":0.1003970729},
{"learn":[133909.8571],"iteration":874,"passed_time":0.6972648529,"remaining_time":0.0996092647},
{"learn":[133862.9435],"iteration":875,"passed_time":0.6980271811,"remaining_time":0.09880750052},
{"learn":[133771.7591],"iteration":876,"passed_time":0.6987767776,"remaining_time":0.09800404064},
{"learn":[133730.2373],"iteration":877,"passed_time":0.6995957704,"remaining_time":0.09721034623},
{"learn":[133673.828],"iteration":878,"passed_time":0.7006477705,"remaining_time":0.0964486692},
{"learn":[133641.7302],"iteration":879,"passed_time":0.7013552063,"remaining_time":0.09563934631},
{"learn":[133545.2688],"iteration":880,"passed_time":0.7019988384,"remaining_time":0.09482163652},
{"learn":[133420.3734],"iteration":881,"passed_time":0.7026599709,"remaining_time":0.09400666278},
{"learn":[133296.8281],"iteration":882,"passed_time":0.7032998671,"remaining_time":0.09318922361},
{"learn":[133214.8889],"iteration":883,"passed_time":0.7039788244,"remaining_time":0.0923773118},
{"learn":[133170.0339],"iteration":884,"passed_time":0.7049161065,"remaining_time":0.09159926808},
{"learn":[133134.4354],"iteration":885,"passed_time":0.7055841244,"remaining_time":0.09078621917},
{"learn":[133089.8614],"iteration":886,"passed_time":0.7062456341,"remaining_time":0.08997266815},
{"learn":[133006.2434],"iteration":887,"passed_time":0.7069640028,"remaining_time":0.08916663099},
{"learn":[132943.5866],"iteration":888,"passed_time":0.7076501521,"remaining_time":0.08835676815},
{"learn":[132882.8325],"iteration":889,"passed_time":0.7083254211,"remaining_time":0.08754583857},
{"learn":[132812.0867],"iteration":890,"passed_time":0.7090254887,"remaining_time":0.08673824721},
{"learn":[132726.6059],"iteration":891,"passed_time":0.7099264821,"remaining_time":0.08595522429},
{"learn":[132608.8458],"iteration":892,"passed_time":0.7108546079,"remaining_time":0.08517518818},
{"learn":[132523.2462],"iteration":893,"passed_time":0.7116056527,"remaining_time":0.08437382459},
{"learn":[132397.9143],"iteration":894,"passed_time":0.7123656216,"remaining_time":0.08357362041},
{"learn":[132295.7254],"iteration":895,"passed_time":0.7132362829,"remaining_time":0.08278635427},
{"learn":[132283.7113],"iteration":896,"passed_time":0.7140407664,"remaining_time":0.08199130317},
{"learn":[132176.8859],"iteration":897,"passed_time":0.7149481848,"remaining_time":0.08120792299},
{"learn":[132136.5662],"iteration":898,"passed_time":0.7158970056,"remaining_time":0.08042891832},
{"learn":[132083.5643],"iteration":899,"passed_time":0.7167940156,"remaining_time":0.07964377951},
{"learn":[132023.4263],"iteration":900,"passed_time":0.7176525652,"remaining_time":0.07885416644},
{"learn":[131870.3021],"iteration":901,"passed_time":0.7184296592,"remaining_time":0.07805555055},
{"learn":[131853.5766],"iteration":902,"passed_time":0.7190798982,"remaining_time":0.07724335562},
{"learn":[131796.7877],"iteration":903,"passed_time":0.7197461366,"remaining_time":0.07643321805},
{"learn":[131745.6005],"iteration":904,"passed_time":0.7204937086,"remaining_time":0.07563193627},
{"learn":[131710.0259],"iteration":905,"passed_time":0.7213001382,"remaining_time":0.07483687969},
{"learn":[131664.2995],"iteration":906,"passed_time":0.7220619607,"remaining_time":0.0740372242},
{"learn":[131595.0952],"iteration":907,"passed_time":0.7228349291,"remaining_time":0.07323878136},
{"learn":[131550.9609],"iteration":908,"passed_time":0.7235163962,"remaining_time":0.07243123439},
{"learn":[131506.0445],"iteration":909,"passed_time":0.7242131281,"remaining_time":0.0716254742},
{"learn":[131478.5692],"iteration":910,"passed_time":0.7248877354,"remaining_time":0.07081779194},
{"learn":[131428.9835],"iteration":911,"passed_time":0.7256515023,"remaining_time":0.07001900461},
{"learn":[131367.1155],"iteration":912,"passed_time":0.7263702364,"remaining_time":0.06921600281},
{"learn":[131307.4032],"iteration":913,"passed_time":0.7272441878,"remaining_time":0.0684277901},
{"learn":[131259.9825],"iteration":914,"passed_time":0.7281401181,"remaining_time":0.06764143173},
{"learn":[131197.4226],"iteration":915,"passed_time":0.7287792661,"remaining_time":0.06683128641},
{"learn":[131126.9552],"iteration":916,"passed_time":0.7296851393,"remaining_time":0.06604565601},
{"learn":[131056.7465],"iteration":917,"passed_time":0.7306649379,"remaining_time":0.065266367},
{"learn":[131004.3398],"iteration":918,"passed_time":0.7315873887,"remaining_time":0.06448158704},
{"learn":[130882.735],"iteration":919,"passed_time":0.7324405693,"remaining_time":0.06369048429},
{"learn":[130864.0453],"iteration":920,"passed_time":0.7332233453,"remaining_time":0.06289320769},
{"learn":[130780.5221],"iteration":921,"passed_time":0.7340145932,"remaining_time":0.06209667925},
{"learn":[130721.1517],"iteration":922,"passed_time":0.7348215071,"remaining_time":0.06130146918},
{"learn":[130656.4882],"iteration":923,"passed_time":0.7355903817,"remaining_time":0.06050310499},
{"learn":[130642.1234],"iteration":924,"passed_time":0.7363650936,"remaining_time":0.05970527786},
{"learn":[130605.9339],"iteration":925,"passed_time":0.7371233535,"remaining_time":0.05890618592},
{"learn":[130548.594],"iteration":926,"passed_time":0.7377843443,"remaining_time":0.05809952226},
{"learn":[130497.3285],"iteration":927,"passed_time":0.738454872,"remaining_time":0.05729391249},
{"learn":[130438.3596],"iteration":928,"passed_time":0.7391086633,"remaining_time":0.05648731442},
{"learn":[130396.3835],"iteration":929,"passed_time":0.7398001005,"remaining_time":0.05568387853},
{"learn":[130374.0585],"iteration":930,"passed_time":0.7404986143,"remaining_time":0.05488120772},
{"learn":[130291.2292],"iteration":931,"passed_time":0.7411726149,"remaining_time":0.0540769719},
{"learn":[130236.7802],"iteration":932,"passed_time":0.7418216556,"remaining_time":0.05327122286},
{"learn":[130223.211],"iteration":933,"passed_time":0.7424562116,"remaining_time":0.05246478583},
{"learn":[130199.167],"iteration":934,"passed_time":0.7432500317,"remaining_time":0.0516697883},
{"learn":[130162.6113],"iteration":935,"passed_time":0.7439441008,"remaining_time":0.05086797271},
{"learn":[130078.3495],"iteration":936,"passed_time":0.7446689024,"remaining_time":0.05006845342},
{"learn":[129969.4217],"iteration":937,"passed_time":0.7454032833,"remaining_time":0.04926972662},
{"learn":[129915.4652],"iteration":938,"passed_time":0.7462508836,"remaining_time":0.04847849191},
{"learn":[129853.0589],"iteration":939,"passed_time":0.7471683984,"remaining_time":0.0476915999},
{"learn":[129741.8223],"iteration":940,"passed_time":0.7478703662,"remaining_time":0.04689091563},
{"learn":[129628.537],"iteration":941,"passed_time":0.7485503088,"remaining_time":0.04608908483},
{"learn":[129565.3419],"iteration":942,"passed_time":0.7492019862,"remaining_time":0.04528580404},
{"learn":[129526.4202],"iteration":943,"passed_time":0.7498842336,"remaining_time":0.04448465792},
{"learn":[129510.2159],"iteration":944,"passed_time":0.7505333844,"remaining_time":0.04368183719},
{"learn":[129455.6546],"iteration":945,"passed_time":0.7512777506,"remaining_time":0.04288477646},
{"learn":[129363.136],"iteration":946,"passed_time":0.7519698573,"remaining_time":0.04208490226},
{"learn":[129283.2102],"iteration":947,"passed_time":0.7526326151,"remaining_time":0.04128364555},
{"learn":[129235.1389],"iteration":948,"passed_time":0.7532864398,"remaining_time":0.04048220067},
{"learn":[129202.73],"iteration":949,"passed_time":0.7540323207,"remaining_time":0.03968591161},
{"learn":[129131.0361],"iteration":950,"passed_time":0.7547137878,"remaining_time":0.03888640968},
{"learn":[129091.3804],"iteration":951,"passed_time":0.7553596463,"remaining_time":0.03808536032},
{"learn":[128987.5929],"iteration":952,"passed_time":0.7561827412,"remaining_time":0.03729337758},
{"learn":[128937.8691],"iteration":953,"passed_time":0.7568733081,"remaining_time":0.03649493938},
{"learn":[128884.5938],"iteration":954,"passed_time":0.7575079538,"remaining_time":0.03569409206},
{"learn":[128785.5531],"iteration":955,"passed_time":0.7581547873,"remaining_time":0.03489415339},
{"learn":[128734.4949],"iteration":956,"passed_time":0.7587967871,"remaining_time":0.0340943175},
{"learn":[128710.2898],"iteration":957,"passed_time":0.7594462901,"remaining_time":0.03329514007},
{"learn":[128627.697],"iteration":958,"passed_time":0.7601868976,"remaining_time":0.03250016976},
{"learn":[128558.3975],"iteration":959,"passed_time":0.7611298843,"remaining_time":0.03171374518},
{"learn":[128522.0561],"iteration":960,"passed_time":0.7621002887,"remaining_time":0.03092810745},
{"learn":[128439.7738],"iteration":961,"passed_time":0.7630740569,"remaining_time":0.03014221846},
{"learn":[128393.6611],"iteration":962,"passed_time":0.7639684028,"remaining_time":0.02935288775},
{"learn":[128349.8553],"iteration":963,"passed_time":0.7650786159,"remaining_time":0.0285714006},
{"learn":[128323.4217],"iteration":964,"passed_time":0.7662175925,"remaining_time":0.02779027538},
{"learn":[128265.6035],"iteration":965,"passed_time":0.7675635755,"remaining_time":0.02701569521},
{"learn":[128183.3999],"iteration":966,"passed_time":0.7686038628,"remaining_time":0.026229501},
{"learn":[128141.675],"iteration":967,"passed_time":0.7695595092,"remaining_time":0.02543998378},
{"learn":[128103.7914],"iteration":968,"passed_time":0.7705525957,"remaining_time":0.02465132143},
{"learn":[128086.2898],"iteration":969,"passed_time":0.7715491369,"remaining_time":0.02386234444},
{"learn":[127982.6464],"iteration":970,"passed_time":0.7724700963,"remaining_time":0.02307068259},
{"learn":[127943.7935],"iteration":971,"passed_time":0.7733465484,"remaining_time":0.02227747259},
{"learn":[127886.1658],"iteration":972,"passed_time":0.7740498469,"remaining_time":0.0214792866},
{"learn":[127807.7369],"iteration":973,"passed_time":0.7748075313,"remaining_time":0.02068274724},
{"learn":[127743.1078],"iteration":974,"passed_time":0.775644068,"remaining_time":0.01988830944},
{"learn":[127698.1571],"iteration":975,"passed_time":0.7763535714,"remaining_time":0.01909066159},
{"learn":[127646.1411],"iteration":976,"passed_time":0.7772708002,"remaining_time":0.01829808435},
{"learn":[127611.7305],"iteration":977,"passed_time":0.7781613486,"remaining_time":0.01750465201},
{"learn":[127512.9717],"iteration":978,"passed_time":0.7788318069,"remaining_time":0.01670630025},
{"learn":[127435.156],"iteration":979,"passed_time":0.7795478207,"remaining_time":0.0159091392},
{"learn":[127405.9447],"iteration":980,"passed_time":0.7802927628,"remaining_time":0.01511270387},
{"learn":[127369.8515],"iteration":981,"passed_time":0.7809356144,"remaining_time":0.0143145021},
{"learn":[127343.6436],"iteration":982,"passed_time":0.7816130026,"remaining_time":0.01351721368},
{"learn":[127264.4033],"iteration":983,"passed_time":0.7822583654,"remaining_time":0.01271964822},
{"learn":[127224.3661],"iteration":984,"passed_time":0.7829224576,"remaining_time":0.01192267702},
{"learn":[127199.3537],"iteration":985,"passed_time":0.7835672439,"remaining_time":0.01112570123},
{"learn":[127135.3244],"iteration":986,"passed_time":0.7842259794,"remaining_time":0.01032921756},
{"learn":[127061.8044],"iteration":987,"passed_time":0.7849043252,"remaining_time":0.009533250914},
{"learn":[126969.3688],"iteration":988,"passed_time":0.7855950801,"remaining_time":0.008737660143},
{"learn":[126959.5426],"iteration":989,"passed_time":0.7863568723,"remaining_time":0.00794299871},
{"learn":[126894.1826],"iteration":990,"passed_time":0.7872089567,"remaining_time":0.007149223623},
{"learn":[126796.0088],"iteration":991,"passed_time":0.7880926492,"remaining_time":0.006355585881},
{"learn":[126723.2186],"iteration":992,"passed_time":0.7887650103,"remaining_time":0.005560277011},
{"learn":[126672.4378],"iteration":993,"passed_time":0.7894469599,"remaining_time":0.0047652734},
{"learn":[126629.8412],"iteration":994,"passed_time":0.7901463049,"remaining_time":0.003970584447},
{"learn":[126543.7677],"iteration":995,"passed_time":0.7908158744,"remaining_time":0.003175967367},
{"learn":[126457.1739],"iteration":996,"passed_time":0.7915528449,"remaining_time":0.002381803947},
{"learn":[126415.7408],"iteration":997,"passed_time":0.7924217275,"remaining_time":0.001588019494},
{"learn":[126342.5034],"iteration":998,"passed_time":0.7934215673,"remaining_time":0.0007942157831},
{"learn":[126305.6721],"iteration":999,"passed_time":0.7942518285,"remaining_time":0}
]}